Workbook

Sheet Portada
B10: Inventario del Portafolio de Aplicaciones (APM)
B12: Proyecto:
B13: Gestión del Portafolio de Aplicaciones — Modelo TIME de Gartner

Sheet README
B2: Gestión del Portafolio de Aplicaciones — Modelo TIME de Gartner
B3: Omnisys S.A. de C.V. · Gobierno de TI y Reportes
B5: 📋 Estructura del Libro de Trabajo
B6: Hoja | C6: Descripción
B7: Inventory | C7: Registro principal de APM — una fila por aplicación. Las celdas amarillas son para llenar.
B8: TIME Assessment | C8: Desglose de criterios de calificación por aplicación (Valor de Negocio + Salud Técnica).
B9: Dashboard | C9: KPIs calculados automáticamente: conteo por cuadrante TIME, costo total, riesgo de EOL.
B10: Lookups | C10: Listas de referencia utilizadas por los menús desplegables de validación de datos en todo el libro.
B12: ⬛ Modelo TIME de Gartner — Definición de Cuadrantes
B13: TOLERATE ⏸ | C13: Bajo Valor de Negocio + Alta Salud Técnica. Mantener en operación, minimizar el gasto; planear su retiro.
B14: INVEST ✅ | C14: Alto Valor de Negocio + Alta Salud Técnica. Incrementar la inversión, mejorar capacidades.
B15: MIGRATE 🔄 | C15: Alto Valor de Negocio + Baja Salud Técnica. Modernizar o reemplazar la plataforma; conservar la función.
B16: ELIMINATE ❌ | C16: Bajo Valor de Negocio + Baja Salud Técnica. Dar de baja lo antes posible; recuperar el costo de licencias/infraestructura.
B18: 🎨 Convención de Colores (hoja Inventory)
B19: Relleno amarillo | C19: Celda de entrada — dato a capturar por el dueño de TI / equipo APM.
B20: Texto negro | C20: Fórmula — no editar directamente.
B21: INVEST (verde) | C21: Disposición TIME calculada automáticamente a partir de las calificaciones en las columnas T y U.
B22: MIGRATE (naranja)
B23: TOLERATE (azul)
B24: ELIMINATE (rojo)
B25: Texto gris itálica | C25: Sin información — se revisó toda la documentación disponible y no se encontró ese dato para esa aplicación.
B26: Texto ámbar itálica
B28: 📊 Guía de Calificación — Valor de Negocio (1–5)
B29: 5 — Esencial | C29: Habilita directamente los ingresos o servicios de cara al cliente. No hay alternativa viable.
B30: 4 — Importante | C30: Soporte significativo a procesos. Es posible una solución temporal a corto plazo, pero costosa.
B31: 3 — Moderado | C31: Útil pero no crítico. Un proceso manual podría sustituirlo temporalmente.
B32: 2 — Marginal | C32: Usuarios o casos de uso limitados. Se traslapa con otras herramientas.
B33: 1 — Mínimo
B35: 🔧 Guía de Calificación — Salud Técnica (1–5)
B36: 5 — Excelente | C36: Arquitectura moderna, con soporte del proveedor, sin defectos conocidos, pruebas automatizadas.
B37: 4 — Bueno | C37: Estable, con soporte, deuda técnica menor.
B38: 3 — Aceptable | C38: Deuda técnica moderada, documentación limitada, despliegues manuales.
B39: 2 — Deficiente | C39: Plataforma envejecida, próxima a EOL, backlog de defectos considerable.
B40: 1 — Crítico
B42: 🔄 Cadencia de Gobierno
B43: Revisión Anual | C43: Reevaluación completa del portafolio. Actualizar todas las calificaciones, costos y disposiciones TIME.
B44: Revisión Trimestral | C44: Revisar las aplicaciones marcadas como Migrate o Eliminate. Actualizar EOL y estatus del proyecto.
B45: Alta de Nueva Aplicación | C45: Toda aplicación nueva debe registrarse en Inventory antes de su puesta en producción.
B46: Baja / Desmantelamiento | C46: Actualizar Status → Retiring, definir FEC_BAJA, retirar de la asignación de costos activa.
B49: 🔄 Criticidad Tec
B50: 5 -
B51: 4 -
B52: 3 -
B53: 2 -
B54: 1 -
B56: 🗂️ Fuentes de Datos Externas Utilizadas
B57: Correspondencia_Aplicaciones_APM_vs_Habilitadores.xlsx | C57: Mapeo Aplicativo APM ↔ ID Habilitador, y el responsable que revisó cada mapeo (columna 'Responsable Técnico' del Inventory antes de la corrección: ahora viene de una fuente mejor, ver abajo).
B58: habilitadores tec.xlsx | C58: Catálogo institucional de habilitadores: Responsable funcional / implementación / operación / soporte, URLs, Product Owner, Producto_Componente (usado para Dominio de Negocio).
B59: Diagnóstico Actual de Identidad Digital (Verano 2026) | C59: Usuarios/Volumetría, Estado de ciberseguridad, Datos personales tratados, Nivel de prioridad de integración/migración (usado para estimar Puntaje ST), y Responsable técnico/soporte real por aplicación.
B60: Pestaña 'TIME Assessment' de este mismo libro | C60: Criterios y escala 1–5 usados para Puntaje VN (derivado de Criticidad) y Puntaje ST, y la fórmula de Disposición TIME.
B61: Posible ubicación de los 2 archivos xlsx de arriba | C61: No se localizaron como archivos individuales dentro del índice de carpetas (el índice solo cataloga carpetas, no archivos), pero las carpetas 'SEA/Documentos Adicionales/SEA/SEA/Mapeos' y 'SEA/Documentos Adicionales/SEA/Inventario' son las candidatas más probables por nombre — verificar ahí primero.
B62: Ver carpeta: Mapeos | C62: Ver carpeta: Inventario
B64: 📌 Historial de Versiones
B65: v16 (19-ago-2026) | C65: Segunda pasada de verificación, más exhaustiva, sobre el índice de carpetas SharePoint: se cruzaron también Descripción, Proveedor y Notas de cada aplicativo (no solo el nombre). Se agregaron 7 fuentes parciales nuevas: Qualtrics→Encuesta Cliente VEC, Formulario U4O→Solicitud de Inscripción SF-SEA, Página de oferta VEC y Algolia→Flujo de búsqueda de productos, Portal Unificado→Integración Portal-Drupal, OpenText NAM→carpeta Identidad Digital, OpenPay→Flujo de compra de productos. Se retiró el vínculo de DED (portales VEC): era coincidencia de siglas con 'Presentaciones de avance DED', no evidencia real. Se agregó hipervínculo real a la fuente 'Diagnóstico Actual de Identidad Digital' citada arriba, y un apunte con las 2 carpetas candidatas ('Mapeos' e 'Inventario') donde probablemente estén los 2 xlsx de correspondencia/habilitadores aún no localizados.
B66: v15 (19-ago-2026) | C66: Se agregó la columna 'Fuente de Información (SharePoint)' (hoja Inventory, con columna 'Confianza') cruzando los 49 aplicativos contra el índice de carpetas 'TD - Ecosistema Digital VPAF'. 9 aplicativos con carpeta dedicada confirmada, 5 con evidencia parcial/relacionada, 35 sin carpeta correspondiente en ese índice (pendientes de ubicar en Correspondencia_Aplicaciones_APM_vs_Habilitadores.xlsx / habilitadores tec.xlsx). Se marcaron en Notas 3 pares de filas que comparten el mismo ID Habilitador (filas 10/47, 25/26, 41/52) para validar si es intencional.
B67: v14 | C67: Versión previa recibida como línea base para esta revisión.

Sheet Inventory
A2: ID | F2: Identidad de la Aplicación | Q2: Perfil Técnico | X2: Ciclo de Vida | AA2: Costos de Propiedad | AE2: Calificación APM | AI2: Gobierno | AL2: Riesgo y Cumplimiento | AP2: Valores TEC | AR2: Trazabilidad
A3: # | B3: Revisado | C3: VPAF/Centrales | D3: Decomiso | E3: ID Habilitador | F3: Habilitador (Aplicación) | G3: Descripción | H3: Producto_Componente:Title | I3: Producto_Componente | J3: Dueño Negocio (Product Owner) | K3: Responsable Técnico | L3: Responsable funcional | M3: Responsable de implementación | N3: Responsable de operación | O3: Responsable de soporte | P3: Proveedor | Q3: Nivel de customización | R3: Hosting | S3: Stack Tecnológico | T3: Dirección URL (PROD) | U3: Dirección URL (DEVL) | V3: Dirección URL (PPRD) | W3: Versión | X3: Primer Día Producción | Y3: Fin de Soporte | Z3: Usuarios Activos | AA3: Costo Licencias($) | AB3: Costo Infraestructura ($) | AC3: Soporte Anual ($) | AD3: Costo Total Anual ($) | AE3: Criticidad | AF3: Puntaje VN (1–5) | AG3: Puntaje ST (1–5) | AH3: Disposición TIME | AI3: Fecha Última Evaluación | AJ3: Próx Revisión | AK3: Estatus | AL3: Integraciones # | AM3: Clasificación de Datos | AN3: Etiquetas de Cumplimiento | AO3: Notas | AP3: Ecosistema | AQ3: Criticidad | AR3: Fuente de Información (SharePoint) | AS3: Confianza
A4: 1 | B4: Si | E4: 0109-HTI-001-TRXO | F4: SEA | G4: Gestión académica core: inscripciones, calificaciones, aprovisionamiento de usuarios; integra Salesforce, Canvas, Cypher, portales de registro y pago | H4: 15. Aprendizaje para el futuro | I4: ATV02. Gestión Académica | J4: Ernesto (solo nombre de pila; fuente: Correspondencia_Aplicaciones_APM_vs_Habilitadores.xlsx) | K4: Adrián Leonel Figueroa Ramírez | L4: claudia.arellano@tec.mx | M4: adrian.figueroa@tec.mx | N4: Adrian -> Uman Diez | O4: Adrian -> Uman Diez | P4: Oracle | Q4: Custom Development | R4: On-Premises | S4: Java (custom, equipo VPAF) | T4: Sin información | U4: Sin información | V4: Sin información | W4: Sin información | X4: Sin información | Y4: Sin información | Z4: 1,206 usuarios registrados en el portal de SEA (fuente: Usuarios SEA.xls). Desglose por tipo de perfil: Superusuario 622, Comercial 315, Líder de proyecto cerrados 100, Control escolar 75, Ingresos 39, Líder prospección 20, Egresos 12, Mercadotecnia 7, Vivencia 5, Prospección 4, Comercialización VIPEC 2, Logístico 2, Líder de proyecto abiertos 2, Prospección y comercial 1. | AA4: 0 | AB4: 0 | AC4: 0 | AD4: 0 | AE4: Mission Critical | AF4: 4 | AG4: 1 | AH4: =IF(AND(AF4>=3,AG4>=3),"Invest",IF(AND(AF4>=3,AG4<3),"Migrate",IF(AND(AF4<3,AG4>=3),"Tolerate","Eliminate"))) -> Migrate | AI4: 46227 | AJ4: 46592 | AK4: Active | AL4: 0 | AM4: Confidential | AN4: LFPDPPP | AO4: Gestión académica core: inscripciones, calificaciones, aprovisionamiento de usuarios; integra Salesforce, Canvas, Cypher, portales de registro y pago Hallazgo 21-sep-2026 (revisión profunda de archivos Excel de las carpetas conectadas): (1) Usuarios — 1,206 usuarios internos reales identificados con desglose por tipo de perfil (ver columna Usuarios Activos; fuente: Usuarios SEA.xls, carpeta Evidencia y platicas\SEA). (2) Alumnos — 57,702 registros reales de alumnos con acceso al sistema (fuente: AlumnosDatos.xlsx, Repositorio TD-Ecosistema Digital VPAF\Documentos Adicionales\SEA\SEA; solo se registra el conteo por tratarse de datos personales). (3) Modelo de datos — esquema real de 13 tablas de la base de datos (controlprogramas, datospersonales, controlprogramas_datosadicionales, datosmodulos, sesiones, asignacionprofesores, datosprofesores, profesoresgastosreales, pagotemporal, solicitudesrecibidas, controlalumnos, usuariounico, sincronizacionsistemas; fuente: TablasImportantesSEA.xlsx). (4) Procesos — 71 procesos/subprocesos funcionales de SEA (líneas U4P y U4O) y 29 mapeos técnicos (fuente: ATV Listado de procesos.xlsx). (5) Automatizaciones — 991 automatizaciones reales de Salesforce/VEC ligadas a SEA, cada una con su propio horario de ejecución (fuente: Automatizaciones flujos SF VEC (U4P y U4O).xlsx). Archivos 3-5 ubicados en Repositorio TD-Ecosistema Digital VPAF\Documentos Adicionales\SEA\Documentación Datos\Documentación SEA. | AP4: VEC | AQ4: 5 | AR4: SEA - carpeta principal | AS4: Confirmada
A5: 2 | B5: Si | E5: 5083-HTI-001-TRXO | F5: Middleware Comercial B2C | G5: Puente de datos / integración entre HubSpot, Salesforce, SEA y Looker; complementa leads y mueve registros | H5: Sin información | I5: Sin información | J5: Ernesto (solo nombre de pila; fuente: Correspondencia_Aplicaciones_APM_vs_Habilitadores.xlsx) | K5: Victor Rafael Tena | L5: victor.tena@tec.mx | M5: victor.tena@tec.mx | N5: victor.tena@tec.mx | O5: victor.tena@tec.mx | P5: AWS | Q5: Custom Development | R5: Cloud-PaaS | S5: AWS (RDS, S3); .Net C#, código sin login propio | T5: https://sso-saml.tec.mx | U5: https://sso-saml-dev.tec.mx | V5: https://sso-saml-qa.tec.mx | W5: Sin información | X5: Sin información | Y5: Sin información | Z5: De acuerdo a sesiones previas con Gobierno de datos, se tiene un estimado de 1,800,000 registros en RDS (leads desde 2019 a 2025) | AA5: 0 | AB5: 0 | AC5: 0 | AD5: 0 | AE5: Medium | AF5: 4 | AG5: 3 | AH5: =IF(AND(AF5>=3,AG5>=3),"Invest",IF(AND(AF5>=3,AG5<3),"Migrate",IF(AND(AF5<3,AG5>=3),"Tolerate","Eliminate"))) -> Invest | AI5: Sin información | AJ5: Sin información | AK5: Under Evaluation | AL5: Sin información | AM5: Restricted | AO5: Puente de datos / integración entre HubSpot, Salesforce, SEA y Looker; complementa leads y mueve registros | AP5: VEC | AQ5: 2 | AR5: No se encontró carpeta correspondiente en el índice de SharePoint | AS5: No encontrada
A6: 3 | B6: Si | E6: 0606-HTI-001-TRXC | F6: PASE | G6: Gestión de identidad y talento académico (expertos, candidatos); historial >115K registros | H6: 08. Colaboradores | I6: CLB05. Gestión de Talento | J6: Erik Sandoval Gutiérrez (esgutierrez@tec.mx) — Líder de Inteligencia Comercial | K6: Angelina Alarcón Romero | L6: iván Valdovinos | M6: Angelina Alarcón Romero | N6: anacopeliaalvarado@tec.mx -> Uman Diez | O6: esgutierrez@tec.mx -> Uman Diez | P6: Desarrollo interno ITESM–VPAF (Erik Sandoval Gutiérrez, L01260117); infraestructura en Azure | Q6: Custom Development | R6: Cloud-IaaS (Azure VM) | S6: ASP.NET / .NET Framework 4.8 sobre IIS 10; SQL Server 2012 + SSIS; librerías ClosedXML, Newtonsoft.Json, ZingChart, jQCloud, Font Awesome 4.7 | T6: https://pase.tec.mx/ITESM/Interno/Talento/Forms/01/REVEC_Login | U6: https://dev.iportafolio.app | V6: https://dev.iportafolio.app | W6: Componentes fuera de soporte del fabricante: SQL Server 2012 (12/07/2022) y Windows 10 (14/10/2025) | X6: Sin información | Y6: Sin información | Z6: Aproximadamente 5,000 expertos han dejado información en la plataforma. De esos, alrededor de 2,500 expertos han tenido participación activa en proyectos o evaluaciones. | AA6: 0 | AB6: 0 | AC6: 0 | AD6: 0 | AE6: Medium | AF6: 3 | AG6: 2 | AH6: =IF(AND(AF6>=3,AG6>=3),"Invest",IF(AND(AF6>=3,AG6<3),"Migrate",IF(AND(AF6<3,AG6>=3),"Tolerate","Eliminate"))) -> Migrate | AI6: 46251 | AJ6: 2027-08-17 | AK6: Active | AL6: 7 | AM6: Confidential | AN6: Datos personales (LFPDPPP): RFC, CURP, correo, teléfono, fotografía. Avisos de Privacidad Candidatos / Empleados / Educación Continua. Contraseñas cifradas en BD. Sin SSO institucional. | AO6: Gestión de identidad y talento académico (expertos, candidatos); historial >115K registros Ambientes: solo PROD. No existen DEVL, PPRD ni Capacitación (Arquitectura del Sistema §6, V1.9 del 03-Jul-2024). URL corregida a pase.tec.mx. Las direcciones iportafolio.app pertenecen a otro habilitador (responsable Angelina Alarcón), no a PASE. Infraestructura: dos instancias en Azure VM (app IIS + BD SQL Server 2012 con SSIS). Riesgo de obsolescencia tecnológica. Autenticación nativa confirmada por documento oficial: correo + contraseña cifrada en BD, para internos y expertos externos. No usa Azure AD. Base de datos: 48 stored procedures en 12 categorías, 5 de criticidad alta y 3 ligados a APIs públicas (corte 25/05/2026). Integración pendiente PASE → Drupal (INT-R1-002 v2.2, junio 2026): riesgo D6 BLOQUEANTE por acceso de red a SQL Server. Contacto: Erik Sandoval. Las 7 integraciones son: Qualtrics (mensual vía SSIS), archivo GyT de categorización (diario), Google Maps API, API U4P Semblanza hacia maestriasydiplomados.tec.mx, API iPortafolio, Territorium (enlace académico) y CRM Empresas. | AP6: VEC | AQ6: 3 | AR6: No se encontró carpeta correspondiente en el índice de SharePoint | AS6: No encontrada
A7: 4 | B7: Si | E7: 0605-HIT-001-TRXC | F7: iPortafolio | G7: Sistema con IA generativa para construcción de propuestas comerciales; consume Salesforce y PASE | H7: 15. Aprendizaje para el futuro | I7: ATV03-1. Atracción y Venta | J7: Ernesto (solo nombre de pila; fuente: Correspondencia_Aplicaciones_APM_vs_Habilitadores.xlsx) | K7: Angelina Alarcón Romero | L7: angelina.alarcon@tec.mx | M7: angelina.alarcon@tec.mx | N7: luis.chitala@tec.mx | O7: luis.chitala@tec.mx | P7: Microsoft Azure | Q7: Custom Development | R7: Hybrid | S7: Django + Azure AD | T7: https://iportafolio.app | U7: https://dev.iportafolio.app | V7: https://dev.iportafolio.app | W7: Sin información | X7: Sin información | Y7: Sin información | Z7: Actualmente 121 usuarios (Asesores de organizaciones y equipo de la VEC). 1500 propuestas acumuladas en dos años 20 a 25 propuestas nuevas por quincena | AA7: 0 | AB7: 0 | AC7: 0 | AD7: 0 | AE7: Medium | AF7: 3 | AG7: 4 | AH7: =IF(AND(AF7>=3,AG7>=3),"Invest",IF(AND(AF7>=3,AG7<3),"Migrate",IF(AND(AF7<3,AG7>=3),"Tolerate","Eliminate"))) -> Invest | AI7: Sin información | AJ7: Sin información | AK7: Active | AL7: Sin información | AM7: Confidential | AO7: Sistema con IA generativa para construcción de propuestas comerciales; consume Salesforce y PASE | AP7: VEC | AQ7: 3 | AR7: No se encontró carpeta correspondiente en el índice de SharePoint | AS7: No encontrada
A8: 5 | B8: Si | E8: 0613-HTI-001-TRXO | F8: Ticket DAP | G8: Levantamiento y gestión de tickets internos de soporte operativo; integrado con Salesforce y SEA | H8: 15. Aprendizaje para el futuro | I8: ATV01. Compra y Pago | J8: Laura (solo nombre de pila; fuente: Correspondencia_Aplicaciones_APM_vs_Habilitadores.xlsx) | K8: Víctor Rafael Tena Ojeda | L8: victor.tena@tec.mx | M8: victor.tena@tec.mx | N8: victor.tena@tec.mx | O8: victor.tena@tec.mx | P8: Desarrollo interno (Tec de Monterrey) | Q8: Custom Development | R8: Cloud-SaaS | S8: Python (FastAPI) sobre Docker | T8: https://www.tecdap.net/help | U8: https://www.tecdap.net/help_dev | V8: Sin información | W8: Sin información | X8: Sin información | Y8: Sin información | Z8: 160.0 | AA8: 0 | AB8: 0 | AC8: 0 | AD8: 0 | AE8: Medium | AF8: 3 | AH8: =IF(AND(AF8>=3,AG8>=3),"Invest",IF(AND(AF8>=3,AG8<3),"Migrate",IF(AND(AF8<3,AG8>=3),"Tolerate","Eliminate"))) -> Migrate | AI8: Sin información | AJ8: Sin información | AK8: Active | AL8: Sin información | AM8: Confidential | AN8: Sin información | AO8: Levantamiento y gestión de tickets internos de soporte operativo; integrado con Salesforce y SEA | AP8: VEC | AQ8: 3 | AR8: No se encontró carpeta correspondiente en el índice de SharePoint | AS8: No encontrada
A9: 6 | B9: Si | E9: 0495-HTI-001-SDMC | F9: Service Now (ex CASEC) | G9: Mesa de servicio institucional, atención de tickets de colaboradores | H9: Sin información | I9: Sin información | J9: alan.bustamante@tec.mx | K9: Cada dueño -> Hoy se centralizan con Blanca Mata | L9: Miguel Burgoin / Blanca Mata | M9: jebreyes@tec.mx | N9: josemiguel@tec.mx | O9: oscar.rdz@tec.mx | P9: ServiceNow | Q9: Commercial Off-the-Shelf | R9: Cloud-SaaS | S9: ServiceNow (federado MiTec) | T9: Sin información | U9: Sin información | V9: Sin información | W9: Sin información | X9: Sin información | Y9: Sin información | Z9: Más de 300 usuarios de la VPAF que tienen acceso a levantar tickets y cerca de 30 analistas que los resuelve | AA9: 0 | AB9: 0 | AC9: 0 | AD9: 0 | AE9: Medium | AF9: 3 | AG9: 2 | AH9: =IF(AND(AF9>=3,AG9>=3),"Invest",IF(AND(AF9>=3,AG9<3),"Migrate",IF(AND(AF9<3,AG9>=3),"Tolerate","Eliminate"))) -> Migrate | AI9: Sin información | AJ9: Sin información | AK9: Active | AL9: Sin información | AM9: Restricted | AN9: Sin información | AO9: Mesa de servicio institucional, atención de tickets de colaboradores | AP9: VEC | AQ9: 3 | AR9: DIR-015 - TecBot VPAF-Service Now (solo integración con TecBot) | AS9: Parcial / relacionada
A10: 7 | B10: Si | E10: 5149-VPA-001-BIPC | F10: Sistema de Rúbricas / Perfilador | G10: Perfilador de prospectos antes de inscripción; ~5,000 aprendedores hacen la prueba | H10: Sin información | I10: Sin información | J10: nlopeznegrete@tec.mx | K10: Víctor Rafael Tena Ojeda | L10: Víctor Rafael Tena Ojeda | M10: Víctor Rafael Tena Ojeda | N10: Víctor Rafael Tena Ojeda | O10: Víctor Rafael Tena Ojeda | P10: Google + Azure | Q10: Custom Development | R10: Hybrid | S10: PHP + MySQL (auth Google + Azure) | T10: Sin información | U10: Sin información | V10: Sin información | W10: Sin información | X10: Sin información | Y10: Sin información | Z10: 10 usuarios que obtienen información. 5 mil aprendedores que hacen la prueba (usuarios que agregan información). | AA10: 0 | AB10: 0 | AC10: 0 | AD10: 0 | AE10: Low | AF10: 1 | AG10: 2 | AH10: =IF(AND(AF10>=3,AG10>=3),"Invest",IF(AND(AF10>=3,AG10<3),"Migrate",IF(AND(AF10<3,AG10>=3),"Tolerate","Eliminate"))) -> Eliminate | AI10: Sin información | AJ10: Sin información | AK10: Active | AL10: Sin información | AM10: Sin información | AO10: ⚠ Verificar: ID Habilitador también asignado a fila 47 ("Buscador / Search Bar"). | AP10: VEC | AQ10: 2 | AR10: No se encontró carpeta correspondiente en el índice de SharePoint | AS10: No encontrada
A11: 8 | B11: Si | E11: Sin información | F11: MICASA | G11: Sitio informativo para profesores/expertos; concentra recursos y comunicaciones | H11: Sin información | I11: Sin información | J11: Sin información | K11: Ana Copelia Alvarado Zepeda | L11: Ana Copelia Alvarado Zepeda | M11: Ana Copelia Alvarado Zepeda | N11: Ana Copelia Alvarado Zepeda | O11: Ana Copelia Alvarado Zepeda | P11: Google | Q11: Custom Development | R11: Cloud-PaaS | S11: Google Sites | T11: Sin información | U11: Sin información | V11: Sin información | W11: Sin información | X11: Sin información | Y11: Sin información | Z11: N/A | AA11: 0 | AB11: 0 | AC11: 0 | AD11: 0 | AE11: Low | AF11: 2 | AH11: =IF(AND(AF11>=3,AG11>=3),"Invest",IF(AND(AF11>=3,AG11<3),"Migrate",IF(AND(AF11<3,AG11>=3),"Tolerate","Eliminate"))) -> Eliminate | AI11: Sin información | AJ11: Sin información | AK11: Retiring | AL11: Sin información | AM11: Internal | AN11: Sin información | AO11: Sitio informativo para profesores/expertos; concentra recursos y comunicaciones | AP11: VEC | AQ11: 2 | AR11: No se encontró carpeta correspondiente en el índice de SharePoint | AS11: No encontrada
A12: 9 | B12: Si | E12: Sin información | F12: Legismex | G12: Sitio del centro de tecnologías para el desarrollo sostenible, contenidos jurídicos/normativos para empresas | H12: Sin información | I12: Sin información | J12: Sin información | K12: María Antonia Garza Jasso | L12: María Antonia Garza Jasso | M12: María Antonia Garza Jasso | N12: María Antonia Garza Jasso | O12: María Antonia Garza Jasso | P12: Sin información | Q12: Custom Development | R12: Sin información | S12: Front en servidor externo (tecnología por confirmar) | T12: Sin información | U12: Sin información | V12: Sin información | W12: Sin información | X12: Sin información | Y12: Sin información | Z12: No especificado, pero limitado a empresas registradas manualmente 230 empresas y son entre 850 y 900 usuarios | AA12: 0 | AB12: 0 | AC12: 0 | AD12: 0 | AE12: Low | AF12: 2 | AG12: 4 | AH12: =IF(AND(AF12>=3,AG12>=3),"Invest",IF(AND(AF12>=3,AG12<3),"Migrate",IF(AND(AF12<3,AG12>=3),"Tolerate","Eliminate"))) -> Tolerate | AI12: Sin información | AJ12: Sin información | AK12: Active | AL12: Sin información | AM12: Sin información | AN12: Sin información | AO12: Sitio del centro de tecnologías para el desarrollo sostenible, contenidos jurídicos/normativos para empresas | AP12: VEC | AQ12: 2 | AR12: No se encontró carpeta correspondiente en el índice de SharePoint | AS12: No encontrada
A13: 10 | B13: Si | E13: 0238-HTI-001-MKAC | F13: HubSpot | G13: Marketing automation y campañas; centraliza leads de U4O y U4P; integra Middleware y Salesforce | H13: Sin información | I13: Sin información | J13: Laura (solo nombre de pila; fuente: Correspondencia_Aplicaciones_APM_vs_Habilitadores.xlsx) | K13: Carlos Franco | L13: Carlos Franco | M13: Israel Martinez israel@tec.mx | N13: Israel Martinez israel@tec.mx | O13: Israel Martinez israel@tec.mx | P13: HubSpot | Q13: SaaS | R13: Cloud-SaaS | S13: HubSpot (SaaS, federado) | T13: Sin información | U13: Sin información | V13: Sin información | W13: Sin información | X13: Sin información | Y13: Sin información | Z13: Usuarios internos -U4O: 4 -U4P: 20 | AA13: 0 | AB13: 0 | AC13: 0 | AD13: 0 | AE13: High | AF13: 4 | AG13: 3 | AH13: =IF(AND(AF13>=3,AG13>=3),"Invest",IF(AND(AF13>=3,AG13<3),"Migrate",IF(AND(AF13<3,AG13>=3),"Tolerate","Eliminate"))) -> Invest | AI13: Sin información | AJ13: Sin información | AK13: Active | AL13: Sin información | AM13: Sin información | AN13: Sin información | AO13: Marketing automation y campañas; centraliza leads de U4O y U4P; integra Middleware y Salesforce | AP13: VEC | AQ13: 4 | AR13: Notificaciones por HubSpot (solo diseños de notificación) | AS13: Parcial / relacionada
A14: 11 | B14: Si | E14: 0027-HTI-001-CRMC | F14: Salesforce | G14: CRM institucional; seguimiento de leads, oportunidades y pipeline comercial; integra Middleware, SEA, HubSpot, PASE | H14: Sin información | I14: Sin información | J14: Ulises (solo nombre de pila; fuente: Correspondencia_Aplicaciones_APM_vs_Habilitadores.xlsx) | K14: Jose Luis Torres (externo) | L14: B2C - Yolanda Magaña B2B - Larisa Díaz / Erik Sandoval | M14: Guillermo Lopez | N14: 1er nivel - Guillermo Lopez 2do nivel - equipo central | O14: 1er nivel - Guillermo Lopez 2do nivel - equipo central | P14: Salesforce | Q14: SaaS | R14: Cloud-SaaS | S14: Salesforce (SaaS, federado) | T14: Sin información | U14: Sin información | V14: Sin información | W14: Sin información | X14: Sin información | Y14: Sin información | Z14: Se tiene registro de 415 activos. | AA14: 0 | AB14: 0 | AC14: 0 | AD14: 0 | AE14: Mission Critical | AF14: 5 | AG14: 2 | AH14: =IF(AND(AF14>=3,AG14>=3),"Invest",IF(AND(AF14>=3,AG14<3),"Migrate",IF(AND(AF14<3,AG14>=3),"Tolerate","Eliminate"))) -> Migrate | AI14: Sin información | AJ14: Sin información | AK14: Active | AL14: Sin información | AM14: Sin información | AN14: Sin información | AO14: CRM institucional; seguimiento de leads, oportunidades y pipeline comercial; integra Middleware, SEA, HubSpot, PASE | AP14: VEC | AQ14: 5 | AR14: JOB-012 - SEA-Pulsar-Salesforce (solo flujo de integración) | AS14: Parcial / relacionada
A15: 12 | E15: 0034-HTI-001-ERPC | F15: SAP (verificar información con Lulu Ayala) | G15: Sistema financiero institucional | H15: 04. Finanzas | I15: FNC05. Información financiera y fiscal | J15: Ulises (solo nombre de pila; fuente: Correspondencia_Aplicaciones_APM_vs_Habilitadores.xlsx) | K15: El soporte y gestión técnica se realiza por área central de TI, mediante tickets para aprovisionamiento y ajustes. | L15: Maria Amelia Estrada | M15: jebreyes@tec.mx | N15: alonso.valenzuela@tec.mx | O15: colivar@tec.mx | P15: SAP | Q15: Commercial Off-the-Shelf | R15: Cloud-SaaS | S15: SAP (federado, gestión central Tec) | T15: Sin información | U15: Sin información | V15: Sin información | W15: Sin información | X15: Sin información | Y15: Sin información | Z15: No se cuenta con un volumen específico, pero se cuenta con información desde el 2006. | AA15: 0 | AB15: 0 | AC15: 0 | AD15: 0 | AE15: Mission Critical | AF15: 5 | AG15: 4 | AH15: =IF(AND(AF15>=3,AG15>=3),"Invest",IF(AND(AF15>=3,AG15<3),"Migrate",IF(AND(AF15<3,AG15>=3),"Tolerate","Eliminate"))) -> Invest | AI15: Sin información | AJ15: Sin información | AK15: Active | AL15: Sin información | AM15: Sin información | AN15: Sin información | AO15: Sistema financiero institucional | AP15: VEC | AQ15: 5 | AR15: No se encontró carpeta correspondiente en el índice de SharePoint | AS15: No encontrada
A16: 13 | E16: 0222-HTI-001-SISO | F16: Banner (verificar información con Lulu Ayala) | G16: Procesos de pago automatizados (uso heredado, conexión institucional) | H16: 16. Línea de Servicio | I16: HT03. Banner | J16: María Alejandra Rohrman Ramos (ale_rohrman@tec.mx) | K16: aoropeza@tec.mx | L16: sandra.garza@tec.mx | M16: aoropeza@tec.mx | N16: antonio.jimenez@tec.mx | O16: oscar.rdz@tec.mx | P16: Ellucian Banner | Q16: SaaS | R16: Cloud-SaaS | S16: Ellucian Banner (gestión central Tec) | T16: https://adminpages.tec.mx/applicationNavigator | U16: Sin información | V16: Sin información | W16: Sin información | X16: Sin información | Y16: Sin información | Z16: Sin información | AA16: 0 | AB16: 0 | AC16: 0 | AD16: 0 | AE16: High | AF16: 4 | AG16: 4 | AH16: =IF(AND(AF16>=3,AG16>=3),"Invest",IF(AND(AF16>=3,AG16<3),"Migrate",IF(AND(AF16<3,AG16>=3),"Tolerate","Eliminate"))) -> Invest | AI16: 46251 | AJ16: 46616 | AK16: Active | AL16: 7 | AM16: Restricted | AN16: Sistema institucional gestionado centralmente; datos financieros de cobranza estudiantil. Acceso federado. | AO16: Procesos de pago automatizados (uso heredado, conexión institucional) Banner es donde se lleva la cuenta del cliente: registra el cargo, el pago y la compensación, y guarda el código de servicio con el que se arma la factura. Tres fuentes confirman este uso. El aplicativo que corresponde a esta descripción es el módulo de cuentas por cobrar, no el de estudiantes que se le había ligado. Hay que corregir el identificador. Se conecta con siete sistemas: Gestor de Pagos, VTEX, Portal de Registro y Pago, MDM Central, SAP, el facturador Interfactura y SEA. Sus catálogos los administra Tech Services: códigos de detalle de cuatro caracteres, uno por moneda, y códigos de servicio de seis caracteres. Problema conocido: las ventas del día se registran en un identificador genérico y no en la cuenta del aprendedor, por eso la factura sale primero a un RFC genérico y luego se refactura. A quién preguntar: María Alejandra Rohrman lleva la facturación, Elva Rivas la administración tecnológica, Zulema Pargas los catálogos y Armando Contreras es el dueño funcional de educación continua. El Tec tiene marcado que falta identificar al dueño institucional. No aparece en el inventario de metadatos de la VPAF. Siguen pendientes costos, ambientes, versión y fechas. | AP16: VEC | AQ16: 4 | AR16: No se encontró carpeta correspondiente en el índice de SharePoint | AS16: No encontrada
A17: 14 | E17: Sin información | F17: Looker Studio | G17: Tableros de visualización para usuarios institucionales (@tec.mx); consume datos procesados de Middleware | H17: 10. Plataforma de Datos (propuesta) | I17: DP01. TEC.data (propuesta) | J17: Sin dueño formal asignado; usuarios registrados en VPAF: Andrés Segura (andres.pantoja@tec.mx), Erik Sandoval (esgutierrez@tec.mx), Victor Tena (victor.tena@tec.mx), Copelia Alvarado (anacopeliaalvarado@tec.mx) | K17: El responsable técnico es José Andrés Segura Pantoja, | L17: Sin información | M17: Sin información | N17: Sin información | O17: Sin información | P17: Google | Q17: SaaS | R17: Cloud-SaaS | S17: Google Looker Studio | T17: https://lookerstudio.google.com | U17: No aplica (SaaS sin ambientes) — coherente con S17 y T17, que ya dicen "No aplica" | V17: No aplica | W17: No aplica | X17: No aplica | Y17: No aplica (servicio SaaS de Google sin fecha de fin de soporte contractual) | Z17: El acceso a los tableros se limita a usuarios institucionales con correos del Tec, principalmente personal de marketing y ventas. No se menciona una cifra exacta, pero se infiere que el volumen es reducido y restringido al personal interno, sin participación de usuarios externos. | AA17: 0 | AB17: 0 | AC17: 0 | AD17: 0 | AE17: Medium | AF17: 3 | AG17: 4 | AH17: =IF(AND(AF17>=3,AG17>=3),"Invest",IF(AND(AF17>=3,AG17<3),"Migrate",IF(AND(AF17<3,AG17>=3),"Tolerate","Eliminate"))) -> Invest | AI17: 46251 | AJ17: 46616 | AK17: Active | AL17: 2 | AM17: Confidential | AN17: Acceso restringido a usuarios institucionales @tec.mx. Federado y gestionado por Tec de Monterrey. Datos de negocio en tableros; sin datos personales sensibles. | AO17: Tableros de visualización para usuarios institucionales (@tec.mx); consume datos procesados de Middleware Looker no está dado de alta en la wiki de habilitadores ni en el inventario de metadatos de la VPAF, pero sí aparece en la arquitectura del ecosistema dentro de la capa de analítica, junto con Power BI y el Data Warehouse del Tec. El propio Tec lo reconoce sin dueño: en su listado lo registra con cuatro personas etiquetadas como usuarios, no como administradores. Son Andrés Segura, Erik Sandoval, Victor Tena y Copelia Alvarado. El primero coincide con el responsable técnico ya capturado. La clasificación de producto es propuesta nuestra, tomada del Data Warehouse del Tec, porque este aplicativo no tiene una asignada. Hay al menos un tablero en producción, el de precios de colegiatura que usa el área de Inscripciones, y está siendo reemplazado por uno nuevo en Power BI con fecha objetivo del 31 de julio de 2026. Se marcó no aplica en versión, fin de soporte y ambientes de desarrollo porque es un servicio en la nube sin versiones ni ambientes propios. El costo en cero está confirmado: la documentación del tablero de colegiaturas dice que no representa costos adicionales. Falta confirmar si hay contratación de la versión de paga. La información del tablero revisado no está catalogada como confidencial, por eso se clasificó como interna. Punto a reportar: hay tableros consumiendo datos institucionales sin registro formal ni dueño. Existe además una regla del ecosistema que separa lo transaccional de lo analítico, y esta herramienta no debe consultar directamente los sistemas de operación. | AP17: VEC | AQ17: 3 | AR17: No se encontró carpeta correspondiente en el índice de SharePoint | AS17: No encontrada
A18: 15 | E18: 0035-TC-002-ERPC | F18: Success Factors | G18: LMS para encuestas y cursos a instructores; ~5,800 usuarios activos | H18: 08. Colaboradores | I18: CLB05. Gestión de Talento | J18: Elva Rivas (elva@tec.mx) | K18: Elva Rivas Ledezma, quien gestiona la operación. El soporte técnico institucional se brinda a través del equipo de TI (Tecnologías de Información). | L18: rogelio.marquez@tec.mx | M18: jcarranz@tec.mx | N18: Elva Rivas (elva@tec.mx) — el registro VPAF la marca como quien gestiona la operación, y H18 ya lo dice así | O18: saranaomi.espana@tec.mx | P18: SAP | Q18: Commercial Off-the-Shelf | R18: Cloud-SaaS | S18: SAP SuccessFactors | T18: Sin información | U18: No aplica (SaaS institucional sin ambiente accesible a VPAF) | V18: No aplica (SaaS institucional sin ambiente accesible a VPAF) | W18: No aplica (SaaS con actualización continua del proveedor) | X18: Sin información | Y18: Sujeto a contrato institucional SAP; no gestionado por VPAF | Z18: -Alumnos:5791 -Profesores -Admin Actualmente se tienen 5,791 usuarios activos, se tiene limite de 10,000 licencias para todos los usuarios. Usuarios nominales identificados en "Aplicaciones Funcionales Vivencia.xlsx" (hoja Hoja1 + hoja Equipo Vivencia), carpeta de evidencia "Evidencia y platicas/Herramientas Vivencia": L03533260 - Hernandez Rodriguez Arlette; L03536134 - Arce Estrada Cristina; L03133597 - Mendoza De Leon Estefania; L03132444 - De la Cruz Ascencio Marcela; L01406546 - Alfredo Ramirez Mejia; L00480574 - Eva Alvarez Sigrist. Esta es informacion adicional/complementaria a la cifra agregada de 5,791 usuarios ya documentada (equipo Vivencia con acceso confirmado a Success Factor para seguimiento al proceso de aprendizaje del aprendedor); no la sustituye. | AA18: 0 | AB18: 0 | AC18: 0 | AD18: 0 | AE18: Medium | AF18: 3 | AG18: 3 | AH18: =IF(AND(AF18>=3,AG18>=3),"Invest",IF(AND(AF18>=3,AG18<3),"Migrate",IF(AND(AF18<3,AG18>=3),"Tolerate","Eliminate"))) -> Invest | AI18: 46251 | AJ18: 2027-08-17 | AK18: Active | AL18: 1 | AM18: Confidential | AN18: Datos personales de colaboradores e instructores (LFPDPPP). Acceso federado institucional, gestionado por Tec de Monterrey. Contrato y cumplimiento a cargo del área central. | AO18: LMS para encuestas y cursos a instructores; ~5,800 usuarios activos Success Factors se usa para encuestas y cursos a instructores. Elva Rivas, Líder de Administración Tecnológica, aparece como administradora y como dueña de los datos en dos fuentes distintas. Su líder es Aramis Arturo Meza Lara. El acceso es federado y la plataforma la gestiona Tec de Monterrey. Los datos viven en la base de datos de Success Factors. Contradicción a resolver: el documento de arquitectura dice que opera independiente del sistema académico, pero el inventario de metadatos indica que sus datos se actualizan al actualizar SEA. Hay que aclarar si existe esa conexión. Por ahora se contó una integración. Guarda datos personales sensibles: género, domicilio, puesto y división organizacional. Por eso se clasificó como confidencial. La suite tiene otros cinco módulos. Hay que definir si el inventario se refiere solo al de capacitación o a toda la suite. Está implementado en cuatro instituciones del sistema Tec, pero nuestro alcance es solo Tec de Monterrey. La wiki no registra responsable de operación. Siguen pendientes costos, ambientes, versión y fechas. | AP18: VEC | AQ18: 3 | AR18: No se encontró carpeta correspondiente en el índice de SharePoint | AS18: No encontrada
A19: 16 | B19: Si | D19: Si | E19: 0017-HTI-001-LMSC | F19: Canvas (ya no se utiliza) | G19: LMS principal para programas U4O y U4P; ~4,750 usuarios; integrado con SEA | H19: 01. Aprendizaje y Enseñanza | I19: TL01. Plataformas de Aprendizaje y Evaluación | J19: Israel Martínez Frías (israel.martinez@tec.mx) | K19: Israel Martínez Frías | L19: bsaldivar@tec.mx | M19: ctvalenzuela@tec.mx | N19: alejandro.ramos@tec.mx | O19: oscar.rdz@tec.mx | P19: Instructure Canvas | Q19: SaaS | R19: Cloud-SaaS | S19: Instructure Canvas | T19: https://educacioncontinuatec.instructure.com | U19: No aplica (SaaS sin ambiente de desarrollo gestionado por VPAF) | V19: No aplica (SaaS sin ambiente de preproducción gestionado por VPAF) | W19: No aplica (SaaS con actualización continua del proveedor Instructure) | X19: Sin información | Y19: Sujeto a contrato con Instructure; pendiente de confirmar con el administrador del contrato | Z19: 4750.0 | AA19: 0 | AB19: 0 | AC19: 0 | AD19: 0 | AE19: High | AF19: 0 | AG19: 0 | AH19: =IF(AND(AF19>=3,AG19>=3),"Invest",IF(AND(AF19>=3,AG19<3),"Migrate",IF(AND(AF19<3,AG19>=3),"Tolerate","Eliminate"))) -> Eliminate | AI19: 46251 | AJ19: 46616 | AK19: Active | AL19: 2 | AM19: Confidential | AN19: Datos personales y académicos de alumnos (LFPDPPP): matrícula, calificaciones y evidencias de aprendizaje. Plataforma SaaS externa con acuerdo institucional. | AO19: LMS principal para programas U4O y U4P; ~4,750 usuarios; integrado con SEA Canvas es la plataforma donde el profesor imparte y evalúa, para los cursos U4P y U4O. Israel Martínez Frías aparece como administrador y dueño de los datos en dos fuentes distintas. Los datos se almacenan en la nube de Canvas administrada por Instructure. El acceso es por SSO. Se conecta con el sistema académico, de donde recibe cursos y personas, y con Banner, que provisiona usuarios de forma automática usando el PIDM como identificador. El paso de calificaciones de regreso al sistema académico lo hace Control Escolar a mano: no hay integración automática. Es una deuda técnica ya reconocida por el Tec. Hay varias instancias. La dirección que se capturó es la de Educación Continua, cuyo dominio amigable es miformacioncontinua.tec.mx. Existen también tec.instructure.com y experiencia21.tec.mx. Hay que confirmar a cuál se refiere el inventario. Existe un reporte de licenciamiento dentro de Canvas. De ahí se puede sacar el número real de usuarios activos. Dato de costo de referencia, de 2019: cada instancia adicional cuesta 1,500 dólares al año. No es el costo total de licenciamiento y hay que actualizarlo. La wiki no tiene dirección de producción para el módulo principal. El módulo de calificaciones sí: https://admincursos.tec.mx/grades | AP19: VEC | AQ19: 4 | AR19: No se encontró carpeta correspondiente en el índice de SharePoint | AS19: No encontrada
A20: 17 | B20: Si | E20: 5169-VPA-001-TRXC | F20: Cypher Learning | G20: LMS para cursos U4O/U4P; ~14,887 asientos; integrado con SEA | H20: 18. APF Ecosistema Digital | I20: ECD03- APF Vivencia y Gestión del Aprendizaje | J20: Luis (solo nombre de pila; fuente: Correspondencia_Aplicaciones_APM_vs_Habilitadores.xlsx) Dato de contrato (Template contratos_11Sep26_V1.xlsx, inventario SAM/HAM en ServiceNow de Uman Amaru Diez Molina, carpeta 'Evidencia y platicas/Uman Diez'): Business Owner registrado = Claudia Arellano Arciga; Vendor = CYPHER LEARNING Inc.; Contract Administrator = Jorge Alberto González López; Approver = Carmen Isabel Reyes Peraza. Pendiente reconciliar con el nombre 'Luis' ya registrado como dueño de negocio desde otra fuente (Correspondencia_Aplicaciones_APM_vs_Habilitadores.xlsx). | K20: Israel Martínez Frías. Contacto adicional confirmado en sesión S-037 (21? 03-sep-2026): Silvino Muñoz Caracas (silvino.munoz@tec.mx). | L20: hcolon@tec.mx | M20: israel.martinez@tec.mx | N20: israel.martinez@tec.mx | O20: israel.martinez@tec.mx | P20: Cypher Learning (LXP/LMS) | Q20: SaaS | R20: Cloud-SaaS | S20: Cypher Learning (LXP/LMS) | T20: https://educacioncontinua.tec.mx/ | U20: http://tecsandbox.neolms.com/ | V20: Sin información | W20: Sin información | X20: Sin información | Y20: Sin información | Z20: 14,887 es un sistema de asientos. | AA20: 0 | AB20: 0 | AC20: 0 | AD20: 0 | AE20: High | AF20: 4 | AG20: 2 | AH20: =IF(AND(AF20>=3,AG20>=3),"Invest",IF(AND(AF20>=3,AG20<3),"Migrate",IF(AND(AF20<3,AG20>=3),"Tolerate","Eliminate"))) -> Migrate | AI20: Sin información | AJ20: Sin información | AK20: Active | AL20: Sin información | AM20: Confidential | AN20: Sin información | AO20: LMS para cursos U4O/U4P; ~14,887 asientos; integrado con SEA Hallazgo sesión S-037 (03-sep-2026): actualmente Cypher Learning opera principalmente mediante cargas manuales; las integraciones con otras plataformas están en proceso de habilitación vía APIs. Forma parte de los 5 aplicativos prioritarios de la iniciativa (junto con PASE, SEA, VTEX/Ecommerce y Portal Unificado). | AP20: VEC | AQ20: 4 | AR20: A001-C01-Plataforma de aprendizaje cypher | AS20: Parcial / relacionada
A21: 18 | B21: Si | E21: 5057-HTI-001-BIPC | F21: Qualtrics | G21: Encuestas NPS, evaluación de programas e instructores; ~2,500 usuarios | H21: Sin información | I21: Sin información | J21: Luis (solo nombre de pila; fuente: Correspondencia_Aplicaciones_APM_vs_Habilitadores.xlsx) | K21: Ricardo Flores | L21: meavil@tec.mx | M21: mm.morales@tec.mx | N21: Sin información | O21: Sin información | P21: Qualtrics (SaaS, parcialmente federado) | Q21: SaaS | R21: Cloud-SaaS | S21: Qualtrics (SaaS, parcialmente federado) | T21: https://itesm.co1.qualtrics.com/ | U21: Sin información | V21: Sin información | W21: Sin información | X21: Sin información | Y21: Sin información | Z21: Actualmente, alrededor de 2,500 | AA21: 0 | AB21: 0 | AC21: 0 | AD21: 0 | AE21: Medium | AF21: 3 | AG21: 3 | AH21: =IF(AND(AF21>=3,AG21>=3),"Invest",IF(AND(AF21>=3,AG21<3),"Migrate",IF(AND(AF21<3,AG21>=3),"Tolerate","Eliminate"))) -> Invest | AI21: Sin información | AJ21: Sin información | AK21: Active | AL21: SEA (MySQL) ↔ Qualtrics ↔ SharePoint: automatización real documentada "Reporte Módulos Qualtrics v2" (Bizagi Modeler v1.0, autor dora.marquez, 08-abr-2025) — SEA se conecta a Qualtrics con credenciales propias, descarga reporte CSV, lo transforma, actualiza archivo maestro en SharePoint, genera Excel procesado, envía correo a destinatarios y archiva históricos; incluye manejo de errores por correo. Fuente: Repositorio TD-Ecosistema Digital VPAF\Documentos Adicionales\SEA\Documentación Datos\Documentación SEA\Automatizaciones\Documentación funcional\Automatización Reportes de Módulos Qualtrics v2.pdf (hallazgo de la décima séptima pasada, 17-sep-2026). | AM21: Sin información | AN21: Sin información | AO21: Encuestas NPS, evaluación de programas e instructores; ~2,500 usuarios | Hallazgo 17-sep-2026: existe una automatización real SEA→Qualtrics→SharePoint documentada en Bizagi (ver columna Integraciones #). | AP21: VEC | AQ21: 3 | AR21: Encuesta Cliente VEC (posible origen de datos NPS) | AS21: Parcial / relacionada
A22: 19 | B22: Si | E22: 5170-VPA-001-TRXC | F22: Accredible (VEC) | G22: Emisión de credenciales y badges digitales para egresados de programas VEC | H22: 18. APF Ecosistema Digital | I22: ECD03- APF Vivencia y Gestión del Aprendizaje | J22: Claudia Arellano (claudia.arellano@tec.mx) | K22: Claudia Arellano Arciga, María del Rosario Pérez Sánchez y Cristina Martínez (equipo de escolares). | L22: j.leon@tec.mx DISPUTADO en sesión S-049 (17-sep-2026): Julieta Adriana León López no acepta ser responsable funcional única de Accredible — no administra la plataforma, no tiene acceso administrativo y no define requerimientos para todas las áreas usuarias. Su equipo (Excelencia Académica y Normatividad) solo valida lineamientos institucionales y autoriza cambios normativos para la emisión de documentos. La plataforma es usada de forma independiente por múltiples áreas (Educación para el Desarrollo, Centro de Idiomas, EGADE, entre otras). Responsable Funcional Institucional: pendiente de definir (ver si existe un Product Owner institucional o un esquema compartido entre áreas). | M22: rosario_perez@tec.mx Confirmado en sesión S-049 (17-sep-2026): María del Rosario Pérez Sánchez funge como administradora operativa de Accredible para la VPAF — gestiona configuraciones, usuarios, permisos, grupos, insignias y documentos, sin acceso al código fuente ni a la infraestructura del proveedor (administración técnica, infraestructura y operación base son responsabilidad del proveedor Accredible, naturaleza SaaS). | N22: rosario_perez@tec.mx -> se entregará a Uman Diez | O22: rosario_perez@tec.mx -> se entregará a Uman Diez | P22: Accredible (plataforma externa) | Q22: SaaS | R22: Cloud-SaaS | S22: Accredible (plataforma externa) | T22: https://educacioncontinua.tec.mx/ | U22: No aplica (SaaS sin ambiente de desarrollo gestionado por VPAF) | V22: No aplica (SaaS sin ambiente de preproducción gestionado por VPAF) | W22: No aplica (SaaS con actualización continua del proveedor) | X22: Sin información | Y22: Sujeto a contrato con Accredible; pendiente de confirmar con el administrador del contrato | Z22: 1,200 usuarios | AA22: 0 | AB22: 0 | AC22: 0 | AD22: 0 | AE22: High | AF22: 3 | AH22: =IF(AND(AF22>=3,AG22>=3),"Invest",IF(AND(AF22>=3,AG22<3),"Migrate",IF(AND(AF22<3,AG22>=3),"Tolerate","Eliminate"))) -> Migrate | AI22: 46251 | AJ22: 46616 | AK22: Active | AL22: 1 | AM22: Confidential | AN22: Datos personales de egresados (LFPDPPP): nombre, matrícula y programa acreditado. Plataforma SaaS externa; credenciales verificables públicamente por diseño. | AO22: Emisión de credenciales y badges digitales para egresados de programas VEC Registro VPAF: responsables Claudia Arellano y María del Rosario Pérez. Descripción registrada: "Expedición de credenciales digitales". CONFLICTO DE DISPOSICIÓN: el registro de arquitectura del Tec (Catálogos ED, hoja 84, corte 01/05/2026) lo marca "En producción" con estrategia "Mantener", mientras este inventario captura "Migrate". Pendiente de resolver con Arturo. El mismo registro clasifica su confidencialidad como Estándar; aquí se captura Confidential por tratarse de datos de egresados con matrícula. Se sostiene el criterio más restrictivo. La wiki del Tec lo lista con institución "Aprendizaje para el futuro" y estatus "Por implementar", lo que contradice el "En producción" del catálogo de arquitectura. Validar cuál es el estado vigente. Dato de contrato (Template contratos_11Sep26_V1.xlsx): Vendor = EdInvent, Inc., dba Accredible; Contract Administrator = Jorge Alberto González López; Approver = Carmen Isabel Reyes Peraza. | AP22: VEC | AQ22: 4 | AR22: DIR-008 - Mis insignias - Portal-Accredible | AS22: Confirmada
A23: 20 | B23: Si | E23: 5086-HTI-001-TRXC | F23: Formulario U4O | G23: Registro y pago para maestrías y diplomados; integra SEA y Salesforce | H23: 03. Facultad | I23: FAC02. Desarrollo de Facultad | J23: Sin información | K23: Proveedor externo: responsable del soporte técnico. María del Rosario Pérez: administra contenido y estructura del formulario. / Gama Logistica | L23: Larisa Díaz y Ana Karen Jimenez | M23: Rosario Perez | N23: Rosario Perez / Gama Logistica | O23: Rosario Perez / Gama Logistica | P23: Proveedor externo (web propietaria) | Q23: Custom Development | R23: Cloud-SaaS | S23: Proveedor externo (web propietaria) | T23: Sin información | U23: https://apps.powerapps.com/play/e/90c43019-1fbe-42ac-95f3-6b777a4cb3a5/a/ff1774e7-0984-48a2-a113-b3812552f586?tenantId=c65a3ea6-0f7c-400b-8934-5a6dc1705645&hint=82fc623d-61c4-4a5a-93e2-48e8edb99d50&sourcetime=1753399355042 | V23: https://apps.powerapps.com/play/e/ffa54977-61ce-49a1-b018-648e027b3954/a/5daa3046-8ec8-40b5-855b-c6f0ce2d3c3e?tenantId=c65a3ea6-0f7c-400b-8934-5a6dc1705645&hint=5656ca9d-cbe0-415c-9662-9b95db11083c&sourcetime=1753399384248 | W23: Sin información | X23: Sin información | Y23: Sin información | Z23: El resultado global muestra un total de 31,699 registros, de los cuales 28,330 corresponden a registros únicos dentro del período analizado. Desglosado por año: -Año 2025: 22,777 registros totales y 20,294 registros únicos en el período. -Año 2024: 8,922 registros totales y 8,423 registros únicos en el período. | AA23: 0 | AB23: 0 | AC23: 0 | AD23: 0 | AE23: High | AF23: 4 | AH23: =IF(AND(AF23>=3,AG23>=3),"Invest",IF(AND(AF23>=3,AG23<3),"Migrate",IF(AND(AF23<3,AG23>=3),"Tolerate","Eliminate"))) -> Migrate | AI23: Sin información | AJ23: Sin información | AK23: Active | AL23: Sin información | AM23: Sin información | AN23: Sin información | AO23: Registro y pago para maestrías y diplomados; integra SEA y Salesforce | AP23: VEC | AQ23: 4 | AR23: Solicitud de Inscripción SF - SEA (integración Salesforce-SEA) | AS23: Parcial / relacionada
A24: 21 | B24: Si | E24: Sin información | F24: Portal de registro y pago | G24: Registro y pago de participantes externos; aprovisiona a SEA | H24: Sin información | I24: Sin información | J24: Sin información | K24: Bryan Moreno (externo) la empresa es Gama Logistica - proveedor Ernesto Martinez Sesión S-050 (17-sep-2026): se identificó a María del Rosario Pérez Sánchez como posible responsable técnica, pendiente de validación formal — dato distinto al ya registrado (Bryan Moreno / Gama Logística); queda como discrepancia sin resolver hasta validación formal con el equipo. | L24: Ricardo Lopez Sesión S-050 (17-sep-2026): Ricardo López Strozzi (lopez.ricardo@tec.mx) identificado como responsable funcional principal, pendiente de validación formal. | M24: rosario_perez@tec.mx | N24: rosario_perez@tec.mx / Gama Logistica Operación diaria confirmada en sesión S-050 (17-sep-2026): ambiente PPRD a cargo de Marco Gerardo Chavira Pérez; Producción a cargo de Ernesto Martínez Arriaga. Soporte especializado: proveedor del habilitador (Gama Logística). No existe una gran cantidad de usuarios administrando el Portal — solo estas dos personas tienen acceso operativo directo. | O24: rosario_perez@tec.mx / Gama Logistica | P24: Proveedor externo (web custom) | Q24: Custom Development | R24: Cloud-SaaS Infraestructura confirmada (Diagrama de infraestructura.drawio, carpeta 'Evidencia y platicas/Portal Registro y Pagos'): AWS Cloud para el Portal de registro y Pago (unidades de cómputo separadas Producción/Desarrollo; autenticación con servicios externos Facebook y Gmail; Cron jobs; 2 bases de datos MySQL), conectado vía Internet al lado de SEA en Azure Cloud (unidad de cómputo Producción, depende de Salesforce; base de datos MariaDB). | S24: Proveedor externo (web custom) Servicios externos identificados en el mismo diagrama: Tec.Pay (pasarela de cobros interna de la institución; depende internamente de Salesforce, OpenPay y Flywire) y un sistema "Middleware" interno desarrollado por el equipo del TEC que ejecuta flujos de trabajo en HubSpot para las notificaciones por correo (recordatorio de inscripción y generación de factura, ambos disparados por Cron). | T24: checkout.tec.mx (mencionado como origen del flujo de pago en los diagramas de secuencia de compra y venta: 'Portal: checkout.tec.mx - solicitudId/origenConexion'). No se confirmó si es la URL pública completa del propio Portal de Registro y Pago o solo del paso de checkout. Confirmado por los diagramas de secuencia reales (Diagrama de secuencia - SEA/ECOMMERCE/EGADE/CEDIAM.txt, mismo folder): checkout.tec.mx SÍ es el paso de checkout/pago del flujo ("Portal: checkout.tec.mx - solicitudId/origenConexion"), usado tanto por el flujo directo de e-commerce como por los flujos asistidos por asesor de SEA y EGADE, vía APIs Gama Logística → Tec.Pay → SEA. | U24: Sin información | V24: Sin información | W24: Sin información | X24: Sin información | Y24: Sin información | Z24: El análisis global muestra un total de 139,381 registros, de los cuales 117,788 son únicos, lo que representa un 15% de registros duplicados. Desglosado por año: -2025: 26,252 registros totales, 23,870 únicos y 9% duplicados. -2024: 27,884 registros totales, 25,537 únicos y 8% duplicados. -2023: 24,092 registros totales, 21,719 únicos y 10% duplicados. -2022: 24,317 registros totales, 22,367 únicos y 8% duplicados. -2021: 21,674 registros totales, 19,978 únicos y 8% duplicados. -2020: 13,655 registros totales, 12,225 únicos y 10% duplicados. -2019: 1,507 registros totales, 1,355 únicos y 10% duplicados. | AA24: 0 | AB24: 0 | AC24: 0 | AD24: 0 | AE24: Medium | AF24: 3 | AH24: =IF(AND(AF24>=3,AG24>=3),"Invest",IF(AND(AF24>=3,AG24<3),"Migrate",IF(AND(AF24<3,AG24>=3),"Tolerate","Eliminate"))) -> Migrate | AI24: Sin información | AJ24: Sin información | AK24: Active | AL24: 3 confirmadas por diagrama de flujo (Bizagi, "Sincronización con portal de registro y pago", autor Israel Romero, v1.0, abr-2026): (1) SEA — creación y publicación de programas, sincronización bidireccional; (2) TLG — consulta horaria de alumnos ("cada hora"); (3) Salesforce — como parte del flujo de venta (Página de maestrías / oferta). No se localizó documentación de integración con VTEX para este habilitador específico. Endpoints reales confirmados por los diagramas de secuencia (mermaid, carpeta 'Evidencia y platicas/Portal Registro y Pagos'): registro/checaExisteEmail, registro/checaBeca, participantes/guardar-usuario, educacionejecutiva/itesm/json/checkusuario, educacionejecutiva/itesm/json/verificarCupo, educacionejecutiva/itesm/json/guardarSolicitud, educacionejecutiva/itesm/json/guardarPago, checkout/regreso_a_tienda (webhook "aviso_transaccion" de Tec.Pay). Además existen 2 canales alternos de adquisición EN ANÁLISIS/DISEÑO (no confirmados en producción): (1) Shopify — requeriría un WebHook nuevo hacia SEA y decidir entre la pasarela propia de Shopify (cobra comisión) o integrar Tec.Pay vía un intermediario del proveedor (Merlioni); (2) VTEX Marketec — ya cuenta con pasarela propia equivalente a Tec.Pay y comunica directamente a Salesforce/Banner, con TEC Milenio como ejemplo de implementación de referencia. | AM24: Sin información | AN24: Sin información | AO24: Registro y pago de participantes externos; aprovisiona a SEA | AP24: VEC | AQ24: 3 | AR24: No se encontró carpeta correspondiente en el índice de SharePoint | AS24: No encontrada
A25: 22 | E25: 5145-HTI-001-TRXC | F25: Página de oferta VEC | G25: Sitio público con oferta educativa (diplomados, certificaciones, maestrías) | H25: 15. Aprendizaje para el futuro | I25: ATV03-1. Atracción y Venta | J25: Carlos Franco (cfrancor@tec.mx) — el registro VPAF lo marca como responsable de "Página de oferta" | K25: Tanto interno como proveedor (Carlos Alberto Martínez) | L25: cfrancor@tec.mx | M25: carlos.msam@tec.mx | N25: cfrancor@tec.mx | O25: Sin información | P25: Ruby on Rails (proveedor externo) | Q25: Custom Development | R25: Cloud-SaaS | S25: Ruby on Rails (proveedor externo) | T25: https://maestriasydiplomados.tec.mx | U25: Sin información | V25: Sin información | W25: Sin información | X25: Sin información | Y25: 2027-11-29 | Z25: No se tiene el volumen de usuarios ya que no tienen acceso | AA25: 0 | AB25: 0 | AC25: 0 | AD25: 0 | AE25: Medium | AF25: 3 | AG25: 4 | AH25: =IF(AND(AF25>=3,AG25>=3),"Invest",IF(AND(AF25>=3,AG25<3),"Migrate",IF(AND(AF25<3,AG25>=3),"Tolerate","Eliminate"))) -> Invest | AI25: 46251 | AJ25: 46616 | AK25: Active | AL25: 2 | AM25: Public | AN25: Sitio público sin autenticación ni captura de datos personales. Contenido de oferta educativa sujeto a lineamientos de marca institucional. | AO25: Sitio público con oferta educativa (diplomados, certificaciones, maestrías) Registro VPAF: responsable Carlos Franco (cfrancor@tec.mx). Descripción registrada: "Sitio público con oferta educativa VEC", sin login. CONFLICTO DE DISPOSICIÓN: el catálogo de arquitectura del Tec (Catálogos ED, hoja 84) registra el "Portal de Mestrias y Diplomados" con estrategia "Eliminar", ajuste de negocio Malo y ajuste de TI Malo, mientras este inventario captura "Invest" con ST 4. Pendiente de resolver con Arturo. Vigencia documentada hasta el 29/11/2027. El Portal Unificado lo reemplaza (Go Live octubre 2026) y el Portal de Compra y Pago asociado vence el 13/10/2026. Integra Algolia como motor de búsqueda del portal. Confianza de correspondencia Media-Alta con el habilitador 5145-HTI-001-TRXC: requiere validación con el Tec antes de darlo por bueno. Responsable de soporte pendiente: no aparece en la wiki ni en el registro VPAF. ⚠ Verificar: ID Habilitador también asignado a fila 26 ("Programa Educación Continua (MiTec)"). | AP25: VEC | AQ25: 3 | AR25: Flujo de búsqueda de productos (Página de oferta integra Algolia, según Notas) | AS25: Parcial / relacionada
A26: 23 | E26: 5145-HTI-001-TRXC | F26: Programa Educación Continua (MiTec) | G26: Conexión con maestrías y diplomados desde portal institucional MiTec | H26: 15. Aprendizaje para el futuro | I26: ATV03-1. Atracción y Venta | J26: Ulises (solo nombre de pila; fuente: Correspondencia_Aplicaciones_APM_vs_Habilitadores.xlsx) | K26: Claudia Arellano Arciga | L26: cfrancor@tec.mx | M26: carlos.msam@tec.mx | N26: cfrancor@tec.mx | O26: oscar.rdz@tec.mx | P26: Microsoft Azure | Q26: Custom Development | R26: Cloud-SaaS | S26: Frontend integrado a MiTec (Azure) | T26: https://maestriasydiplomados.tec.mx | U26: Sin información | V26: Sin información | W26: Sin información | X26: Sin información | Y26: Sin información | Z26: No aplica ya que solo los usuarios entran y se dirigen a las opciones que les interesa consultar | AA26: 0 | AB26: 0 | AC26: 0 | AE26: Medium | AF26: 3 | AG26: 4 | AH26: =IF(AND(AF26>=3,AG26>=3),"Invest",IF(AND(AF26>=3,AG26<3),"Migrate",IF(AND(AF26<3,AG26>=3),"Tolerate","Eliminate"))) -> Invest | AI26: Sin información | AJ26: Sin información | AK26: Active | AL26: Sin información | AM26: Sin información | AN26: Sin información | AO26: Conexión con maestrías y diplomados desde portal institucional MiTec ⚠ Verificar: ID Habilitador también asignado a fila 25 ("Página de oferta VEC"). | AP26: VEC | AQ26: 3 | AR26: No se encontró carpeta correspondiente en el índice de SharePoint | AS26: No encontrada
A27: 24 | B27: Si | E27: 5138-HTI-001-TRXC | F27: DED (portales VEC) | G27: Cuatro portales para Educación para el Desarrollo: registro, pago y entrega de contenidos | H27: 15. Aprendizaje para el futuro | I27: ATV04. Gestión de la Oferta | J27: Daniela de la Rosa (líder de proyecto) — así aparece en el registro VPAF | K27: Equipo DED Neotek (soporte Drupal) - Dev Team Head Bryan Moreno | L27: Karina Martinez | M27: Rosario Perez | N27: Neotek (soporte Drupal) | O27: Neotek (soporte Drupal) | P27: Drupal | Q27: Custom Development | R27: Cloud-SaaS | S27: Drupal (proveedor Neotec) + sitios reconstruidos | T27: https://www.centroscomunitariosdeaprendizaje.org.mx; https://www.formandoformadores.org.mx; https://www.aprendizajeverde.net | U27: Sin información | V27: Sin información | W27: Sin información | X27: CVA desde 2010 / FF desde 2015 / AV desde 2012 | Y27: Sin información | Z27: CVA ~710,000 / FF 42,250 / AV 35,350 / Más Sociedad sin usuarios | AA27: 0 | AB27: 0 | AC27: 0 | AD27: 0 | AE27: High | AF27: 4 | AG27: 4 | AH27: =IF(AND(AF27>=3,AG27>=3),"Invest",IF(AND(AF27>=3,AG27<3),"Migrate",IF(AND(AF27<3,AG27>=3),"Tolerate","Eliminate"))) -> Invest | AI27: 46251 | AJ27: 46616 | AK27: Active | AL27: 4 | AM27: Confidential | AN27: Datos personales de participantes (LFPDPPP) y datos de pago. Portales públicos con registro. Desarrollo y soporte a cargo de proveedor externo (Neotek): aplica cláusula de tratamiento de datos por terceros. | AO27: Cuatro portales para Educación para el Desarrollo: registro, pago y entrega de contenidos Registro VPAF: Daniela de la Rosa (líder de proyecto) y Jesús Alejandro Medina (técnico). Proveedor externo Neotek. El registro también lista "Superate" como ecosistema educativo en línea de la Dirección de Educación para el Desarrollo, con ~150 usuarios internos mensuales y 30-40k externos mensuales. El Centro Virtual de Aprendizaje aparece en VPAF con 1,200,000 usuarios históricos, consistente con los ~710,000 capturados aquí para CVA. DISCREPANCIA DE ALCANCE: este renglón declara cuatro portales, pero en la wiki del Tec solo se localizaron tres bajo el habilitador 5138-HTI-001-TRXC. El cuarto ("Más Sociedad") aparece aquí sin usuarios registrados. Validar con el Tec si forma parte del mismo habilitador o si debe registrarse aparte. La clasificación de datos y las etiquetas de cumplimiento aplican al conjunto de portales; el tratamiento de datos personales está delegado a proveedor externo. ⚠ Nota v16: se descartó el vínculo a la carpeta "Presentaciones de avance DED" — es coincidencia de siglas (gobierno del proyecto Ecosistema Digital), no documentación de este aplicativo (Educación para el Desarrollo). | AP27: VEC | AQ27: 4 | AR27: No se encontró carpeta correspondiente en el índice de SharePoint | AS27: No encontrada
A28: 25 | E28: 0470-HTI-001-TRXC | F28: Marketplace de Talento | G28: Conecta a prospectos egresados con empleadores | H28: Graduway | I28: Sin información | J28: Sin información | K28: Sin información | L28: Sin información | M28: Sin información | N28: Sin información | O28: Sin información | P28: Sin información | T28: Sin información | U28: Sin información | V28: Sin información | W28: Sin información | X28: Sin información | Z28: Sin información | AE28: Medium | AH28: Eliminate | AI28: Sin información | AK28: Sin información | AL28: Sin información | AM28: Sin información | AO28: VEC | AP28: 3 | AQ28: 3 | AR28: No se encontró carpeta correspondiente en el índice de SharePoint | AS28: No encontrada
E29: 5147-HTI-001-TRXC | H29: Marketplace de Socios Formadores | I29: Sin información | J29: Sin información | K29: Sin información | L29: daniel_ayala@tec.mx | M29: gerardo.suarez@tec.mx | N29: mariano_uriostegui@tec.mx | O29: mariano_uriostegui@tec.mx | P29: Sin información | Q29: Custom Development | S29: Node.js;#8;#Java;#9 | T29: https://www.mpstec.mx/ | U29: Sin información | V29: Sin información | W29: Sin información | X29: Sin información | Z29: Sin información | AE29: Medium | AH29: Eliminate | AI29: Sin información | AK29: Sin información | AL29: Sin información | AM29: Sin información | AN29: Plataforma para conectar ácademicos con Socios Formadores para colaborar en proyectos. | AO29: VEC | AP29: 3
E30: 0222-HTI-010-SISO | H30: GURJOBS | I30: Sin información | J30: Sin información | K30: aoropeza@tec.mx | L30: Sin información | M30: aoropeza@tec.mx | N30: antonio.jimenez@tec.mx | O30: Sin información | P30: Keycloak + Azure | Q30: Custom Development | R30: Hybrid | S30: Keycloak + Azure (auth) | T30: Sin información | U30: Sin información | V30: Sin información | W30: Sin información | X30: Sin información | Y30: Sin información | Z30: Sin información | AA30: $0 | AB30: $0 | AC30: $0 | AE30: Medium | AF30: 3 | AH30: Migrate | AI30: Sin información | AJ30: Active | AK30: Sin información | AL30: Sin información | AM30: Sin información | AN30: Conecta a prospectos egresados con empleadores | AO30: VEC | AP30: 3
A31: 26 | B31: Si | E31: Sin información | F31: Nimbi | G31: Seguimiento de participantes y análisis predictivo de aprendizaje; ~75K usuarios | H31: Sin información | I31: Sin información | J31: Sin información | K31: Sin información | L31: hcolon@tec.mx | M31: erika.carrizales@tec.mx | N31: antoniovillanueva_844@tec.mx | O31: antoniovillanueva_844@tec.mx | P31: Proveedor Lapzo Vendor confirmado: NIMBI SPA (Template contratos_11Sep26_V1.xlsx). Contract Administrator / Business Owner registrado en el contrato: Erika Carrizales Ovalle — coincide con el Responsable de implementación ya registrado (erika.carrizales@tec.mx). | Q31: SaaS | R31: Cloud-SaaS | S31: Proveedor Lapzo (LXP/LMS) | T31: Sin información | U31: Sin información | V31: Sin información | W31: Sin información | X31: Sin información | Y31: Sin información | Z31: La plataforma cuenta con alrededor de 75,000 usuarios registrados, incluyendo participantes activos en cursos y programas gratuitos o comerciales. Usuarios reales identificados (Aplicaciones Funcionales Vivencia.xlsx, hoja 'Equipo Vivencia', carpeta 'Evidencia y platicas/Herramientas Vivencia'): L03529466 Villarino Rivera Jesus Francisco, L03567793 Herrera Alvarez Luis Roberto, L01406546 Alfredo Israel Ramírez Mejía, L03572358 Paola Figueroa Islas — uso: gestión de atención a aprendedores y seguimiento a entregables. Nota: la cifra de ~75,000 usuarios ya registrada en esta misma celda coincide textualmente con la de TLG Lapzo (fila #30); posible error de captura de una pasada anterior — se deja señalado, sin corregir por no tener evidencia propia de Nimbi que lo sustente. | AA31: $0 | AB31: $0 | AC31: $0 | AE31: High | AF31: 4 | AH31: Migrate | AI31: Sin información | AJ31: Active | AK31: Sin información | AL31: Sin información | AM31: Sin información | AN31: Seguimiento de participantes y análisis predictivo de aprendizaje; ~75K usuarios | AO31: TLG | AP31: 4 | AQ31: 4 | AR31: No se encontró carpeta correspondiente en el índice de SharePoint | AS31: No encontrada
A32: 27 | E32: Sin información | F32: 1Mentor (validar porque se usaba pero ya no se esta utilizando)* preguntar a Erika/Héctor Colón | G32: Diagnóstico de competencias laborales; ~5,000 usuarios externos mensuales | H32: Sin información | I32: Sin información | J32: Sin información | K32: Sin información | L32: Sin información | M32: Sin información | N32: Sin información | O32: Sin información | P32: 1Mentor | Q32: SaaS | R32: Cloud-SaaS | S32: 1Mentor (SaaS) | T32: Sin información | U32: Sin información | V32: Sin información | W32: Sin información | X32: Sin información | Y32: Sin información | Z32: Sin información | AA32: $0 | AB32: $0 | AC32: $0 | AE32: Medium | AF32: 3 | AH32: Migrate | AI32: Sin información | AJ32: Active | AK32: Sin información | AL32: Sin información | AM32: Sin información | AN32: Diagnóstico de competencias laborales; ~5,000 usuarios externos mensuales | AO32: TLG | AP32: 3 | AQ32: 3 | AR32: No se encontró carpeta correspondiente en el índice de SharePoint | AS32: No encontrada
A33: 28 | B33: Si | E33: 5068-UTM-001-TRXC | F33: Mentorcloud | G33: Creación y gestión de mentorías entre expertos y aprendedores | H33: PIVOTEA | I33: Sin información | J33: Sin información | K33: rosario_perez@tec.mx (debería de ser Silvino Muñoz) | L33: caro_martinez@tec.mx / Octavio Acosta | M33: rosario_perez@tec.mx | N33: TBD al habilitarse sería Uman Diez | O33: TBD al habilitarse sería Uman Diez | P33: Mentorcloud | Q33: Custom Development | R33: Cloud-SaaS | S33: Node.js;#8 | T33: https://pivotea.tecmilab.com.mx/ | U33: Sin información | V33: Sin información | W33: Sin información | X33: Sin información | Y33: Sin información | Z33: Sin información | AA33: $0 | AB33: $0 | AC33: $0 | AE33: Medium | AF33: 3 | AH33: Migrate | AI33: Sin información | AJ33: Active | AK33: Sin información | AL33: Sin información | AM33: Sin información | AN33: Creación y gestión de mentorías entre expertos y aprendedores | AO33: TLG | AP33: 3 | AQ33: 3 | AR33: No se encontró carpeta correspondiente en el índice de SharePoint | AS33: No encontrada
A34: 29 | B34: Si | E34: Sin información | F34: Circle | G34: Comunidad social de TLG; ~50K usuarios histórico (2022-2025) | H34: Sin información | I34: Sin información | J34: Sin información | K34: Silvino Muñoz (Lapzo) — responsable técnico a nivel ecosistema TLG | L34: Isabel Ferguson | M34: erika.carrizales@tec.mx | N34: antoniovillanueva_844@tec.mx | O34: antoniovillanueva_844@tec.mx | P34: Circle.so | Q34: SaaS | R34: Sin información | S34: Circle.so (SaaS) | T34: Sin información | U34: Sin información | V34: Sin información | W34: Sin información | X34: Sin información | Y34: Sin información | Z34: Sin información | AA34: 0 | AB34: 0 | AC34: 0 | AD34: 0 | AE34: Medium | AF34: 3 | AH34: =IF(AND(AF34>=3,AG34>=3),"Invest",IF(AND(AF34>=3,AG34<3),"Migrate",IF(AND(AF34<3,AG34>=3),"Tolerate","Eliminate"))) -> Migrate | AI34: Sin información | AJ34: Sin información | AK34: Active | AL34: Sin información | AM34: Sin información | AN34: Sin información | AO34: Comunidad social de TLG; ~50K usuarios histórico (2022-2025) | AP34: TLG | AQ34: 3 | AR34: No se encontró carpeta correspondiente en el índice de SharePoint | AS34: No encontrada
A35: 30 | B35: Si | E35: Sin información | F35: TLG Lapzo | G35: LMS principal de TLG; entrega de cursos con vigencia | H35: Sin información | I35: Sin información | J35: Sin información | K35: Dentro del equipo administrador se encuentran Erika Carrizales Ovalle y Héctor Alfonso Colón Alvarez, el soporte técnico recae en Silvino Muñoz y en Lapzo como proveedor responsable de la operación y mantenimiento general. | L35: hcolon@tec.mx | M35: erika.carrizales@tec.mx | N35: antoniovillanueva_844@tec.mx | O35: antoniovillanueva_844@tec.mx | P35: Lapzo | Q35: Custom Development | R35: Cloud-SaaS | S35: Firebase + infraestructura Google (proveedor Lapzo) | T35: Sin información | U35: Sin información | V35: Sin información | W35: Sin información | X35: Sin información | Y35: Sin información | Z35: La plataforma cuenta con alrededor de 75,000 usuarios registrados, incluyendo participantes activos en cursos y programas gratuitos o comerciales. Usuarios reales identificados (Aplicaciones Funcionales Vivencia.xlsx, hoja 'Equipo Vivencia'): L01137166 Garcia Gonzalez Ana Lucia, L03063022 Valle Rodriguez Maria Del Carmen, L03529466 Villarino Rivera Jesus Francisco, L03567793 Herrera Alvarez Luis Roberto, L01406546 Alfredo Israel Ramírez Mejía, L03572358 Paola Figueroa Islas. | AA35: 0 | AB35: 0 | AC35: 0 | AD35: 0 | AE35: High | AF35: 4 | AG35: 3 | AH35: =IF(AND(AF35>=3,AG35>=3),"Invest",IF(AND(AF35>=3,AG35<3),"Migrate",IF(AND(AF35<3,AG35>=3),"Tolerate","Eliminate"))) -> Invest | AI35: Sin información | AJ35: Sin información | AK35: Active | AL35: 1 confirmada: GI-001 TLG (LXP) → Service Bus (Pulsar) — evento asíncrono "module.completed" (curso completado, promedio >70) que dispara el flujo de generación de insignias (GI-001→GI-006, incluye Accredible y MDM/OpenText). Fuente: GI-001_Cypher-TLG_Pulsar.docx. La carpeta dedicada "DIR-017 - Portal-TLG (Mi Aprendizaje)" existe en el repositorio pero está vacía (sin ficha de integración construida aún). | AM35: Sin información | AN35: Sin información | AO35: LMS principal de TLG; entrega de cursos con vigencia Dato de contrato (Template contratos_11Sep26_V1.xlsx): Vendor = DECASOL, SA DE CV (Lapzo); Business Owner = Héctor Alfonso Colón Alvarez — coincide con el Responsable funcional ya registrado (hcolon@tec.mx); Contract Administrator = Jorge Alberto González López. | AP35: TLG | AQ35: 4 | AR35: DIR-017 - Portal-TLG (Mi Aprendizaje) | AS35: Confirmada
A36: 31 | E36: Sin información | F36: Mylearning.tec.mx | G36: Sitio público con oferta educativa de TLG | H36: Sin información | I36: Sin información | J36: Sin información | K36: Silvino Muñoz (Lapzo) — responsable técnico a nivel ecosistema TLG | L36: Sin información | M36: Sin información | N36: Sin información | O36: Sin información | P36: Sitio público (sin login) | Q36: Custom Development | R36: Cloud-SaaS | S36: Sitio público (sin login) | T36: Sin información | U36: Sin información | V36: Sin información | W36: Sin información | X36: Sin información | Y36: Sin información | Z36: Sin información | AA36: 0 | AB36: 0 | AC36: 0 | AD36: 0 | AE36: Medium | AF36: 3 | AH36: =IF(AND(AF36>=3,AG36>=3),"Invest",IF(AND(AF36>=3,AG36<3),"Migrate",IF(AND(AF36<3,AG36>=3),"Tolerate","Eliminate"))) -> Migrate | AI36: Sin información | AJ36: Sin información | AK36: Active | AL36: Sin información | AM36: Sin información | AN36: Sin información | AO36: Sitio público con oferta educativa de TLG | AP36: TLG | AQ36: 3 | AR36: No se encontró carpeta correspondiente en el índice de SharePoint | AS36: No encontrada
A37: 32 | E37: Sin información | F37: Plataforma Web Clínicas | G37: Sitio público de venta de productos educativos (campamentos, academias, Club Borregos); incluye datos de menores | H37: Sin información | I37: Sin información | J37: Sin información | K37: Nini Johana Otero Salas (administradora de la plataforma) Ricardo González (Salesforce admin) Lili Mared Ricárdez Vázquez (configuración de formularios y página web) Fernando Matehuala (gestión de licencias Power BI) | L37: Sin información | M37: Sin información | N37: Sin información | O37: Sin información | P37: Salesforce | Q37: Commercial Off-the-Shelf | R37: Hybrid | S37: Salesforce + Fonteva (módulo de ventas) | T37: Sin información | U37: Sin información | V37: Sin información | W37: Sin información | X37: Sin información | Y37: Sin información | Z37: Al tratarse de una plataforma web, no se cuenta con un estimado de usuarios activos ya que no se necesita ingresar con un usuario | AA37: 0 | AB37: 0 | AC37: 0 | AD37: 0 | AE37: Low | AF37: 2 | AG37: 4 | AH37: =IF(AND(AF37>=3,AG37>=3),"Invest",IF(AND(AF37>=3,AG37<3),"Migrate",IF(AND(AF37<3,AG37>=3),"Tolerate","Eliminate"))) -> Tolerate | AI37: Sin información | AJ37: Sin información | AK37: Active | AL37: Sin información | AM37: Sin información | AN37: Sin información | AO37: Sitio público de venta de productos educativos (campamentos, academias, Club Borregos); incluye datos de menores | AP37: VED | AQ37: 2 | AR37: No se encontró carpeta correspondiente en el índice de SharePoint | AS37: No encontrada
A38: 33 | E38: 0027-HTI-012-CRMC | F38: Fonteva (Validar con Ricardo Araujo) | G38: Módulo de gestión de productos y ventas en línea (Campamentos, Eventos) | H38: 16. Línea de Servicio | I38: HT04. Salesforce | J38: Sin información | K38: ricardo.araujo@tec.mx | L38: - | M38: - | N38: - | O38: - | P38: Fonteva sobre Salesforce (federado) | Q38: Commercial Off-the-Shelf | R38: Cloud-SaaS | S38: Fonteva sobre Salesforce (federado) | T38: Sin información | U38: Sin información | V38: Sin información | W38: Sin información | X38: Sin información | Y38: Sin información | Z38: Se cuenta con 6 usuarios administradores de la plataforma | AA38: 0 | AB38: 0 | AC38: 0 | AD38: 0 | AE38: High | AF38: 4 | AH38: =IF(AND(AF38>=3,AG38>=3),"Invest",IF(AND(AF38>=3,AG38<3),"Migrate",IF(AND(AF38<3,AG38>=3),"Tolerate","Eliminate"))) -> Migrate | AI38: Sin información | AJ38: Sin información | AK38: Active | AL38: Sin información | AM38: Sin información | AN38: Sin información | AO38: Módulo de gestión de productos y ventas en línea (Campamentos, Eventos) | AP38: VED | AQ38: 4 | AR38: No se encontró carpeta correspondiente en el índice de SharePoint | AS38: No encontrada
A39: 34 | E39: 3023-HTI-001-WWW | F39: Plataforma Web Centro de Idiomas (Validar con Maria Eugenia Gonzalez) | G39: Sitio de inscripción y gestión académica para cursos de idiomas | H39: Sin información | I39: Sin información | J39: Sin información | K39: Arturo Hernández (interlocutor técnico, director tecnico de cento de idiomas) Andrea Piccolo (Softian, desarrollo externo) | L39: gabygomez74@tec.mx | M39: omar.jimenez@tec.mx | N39: Sin información | O39: Sin información | P39: Softian | Q39: Commercial Off-the-Shelf | R39: Cloud-SaaS | S39: Sistema SICI (proveedor Softian) | T39: http://tec.territorio.la/ | U39: Sin información | V39: Sin información | W39: Sin información | X39: Sin información | Y39: Sin información | Z39: No se tiene registros de cuánta gente visita la páginas Número de usuarios administradores 46 | AA39: 0 | AB39: 0 | AC39: 0 | AD39: 0 | AE39: High | AF39: 4 | AG39: 4 | AH39: =IF(AND(AF39>=3,AG39>=3),"Invest",IF(AND(AF39>=3,AG39<3),"Migrate",IF(AND(AF39<3,AG39>=3),"Tolerate","Eliminate"))) -> Invest | AI39: Sin información | AJ39: Sin información | AK39: Active | AL39: Sin información | AM39: Sin información | AN39: Sin información | AO39: Sitio de inscripción y gestión académica para cursos de idiomas | AP39: VED | AQ39: 4 | AR39: No se encontró carpeta correspondiente en el índice de SharePoint | AS39: No encontrada
A40: 35 | E40: Sin información | F40: Sistema de Inscripción Centro de Idiomas | G40: Plataforma web autónoma para gestión de inscripciones del Centro de Idiomas; trata información personal, académica, médica y administrativa | H40: Sin información | I40: Sin información | J40: Sin información | K40: El soporte técnico y desarrollo están a cargo de Softian, representado por Andrea Piccolo. La administración operativa y comunicación institucional las coordina Arturo Hernández desde el Centro de Idiomas. | L40: Sin información | M40: Sin información | N40: Sin información | O40: Sin información | P40: Softian | Q40: Commercial Off-the-Shelf | R40: Cloud-SaaS | S40: Softian (web propietaria) | T40: Sin información | U40: Sin información | V40: Sin información | W40: Sin información | X40: Sin información | Y40: Sin información | Z40: Falta información específica sobre la cantidad de usuarios activos, sin embargo, se menciona que todos los campus del TEC utilizan el sistema desde 2023, lo que implica una cobertura nacional de alumnos, profesores y personal administrativo. Volumen promedio de usuarios por semestre es de 400 usuarios pudiendo llegar a los 900 anuales. | AA40: 0 | AB40: 0 | AC40: 0 | AD40: 0 | AE40: High | AF40: 4 | AH40: =IF(AND(AF40>=3,AG40>=3),"Invest",IF(AND(AF40>=3,AG40<3),"Migrate",IF(AND(AF40<3,AG40>=3),"Tolerate","Eliminate"))) -> Migrate | AI40: Sin información | AJ40: Sin información | AK40: Active | AL40: Sin información | AM40: Sin información | AN40: Sin información | AO40: Plataforma web autónoma para gestión de inscripciones del Centro de Idiomas; trata información personal, académica, médica y administrativa | AP40: VED | AQ40: 4 | AR40: No se encontró carpeta correspondiente en el índice de SharePoint | AS40: No encontrada
A41: 36 | B41: Si | E41: 0490-HTI-001-TRXC | F41: Market Tec (preguntar con Lulu Ayala) | G41: Motor de pagos conectado al Centro de Idiomas y otros canales | H41: 04. Finanzas | I41: FNC02. Facturación | J41: Brayan (solo nombre de pila; fuente: Correspondencia_Aplicaciones_APM_vs_Habilitadores.xlsx) | K41: jebreyes@tec.mx | L41: saul.zermeno@tec.mx | M41: jebreyes@tec.mx | N41: fmoreira@tec.mx | O41: colivar@tec.mx | P41: Motor de pagos en línea (federado) | Q41: SaaS | R41: Cloud-SaaS | S41: Motor de pagos en línea (federado) | T41: https://market.tec.mx/login?samltec | U41: No aplica (SaaS sin ambientes gestionados por VPAF) | V41: No aplica (SaaS sin ambientes gestionados por VPAF) | W41: No aplica (SaaS con actualización continua del proveedor) | X41: Sin información | Y41: Sujeto a contrato del servicio de pagos; pendiente de confirmar | Z41: Sin información | AA41: 0 | AB41: 0 | AC41: 0 | AD41: 0 | AE41: High | AF41: 4 | AH41: =IF(AND(AF41>=3,AG41>=3),"Invest",IF(AND(AF41>=3,AG41<3),"Migrate",IF(AND(AF41<3,AG41>=3),"Tolerate","Eliminate"))) -> Migrate | AI41: 46251 | AJ41: 46616 | AK41: Active | AL41: 2 | AM41: Confidential | AN41: Datos de pago y transacción. Autenticación federada institucional vía SAML. Aplican requisitos de seguridad en medios de pago y LFPDPPP. | AO41: Motor de pagos conectado al Centro de Idiomas y otros canales ⚠ Verificar: ID Habilitador también asignado a fila 52 ("VTEX"). Autenticación federada institucional mediante SAML, confirmada por la URL de producción (market.tec.mx/login?samltec). Cadena de responsables completa y diferenciada: técnico e implementación jebreyes@tec.mx, funcional saul.zermeno@tec.mx, operación fmoreira@tec.mx, soporte colivar@tec.mx. Dueño de negocio (Product Owner) sin asignar: pendiente de definir. El campo Ecosistema registra "VED"; el resto de los aplicativos del mismo ecosistema registran "VEC". Probable error de captura, no sobrescrito pendiente de validación. Conflicto de consistencia: disposición Migrate con Criticidad High y VN 4, sobre una plataforma SaaS federada sin deuda técnica documentada. Requiere revisar el sustento de la disposición o el puntaje ST. | AP41: VED | AQ41: 4 | AR41: No se encontró carpeta correspondiente en el índice de SharePoint | AS41: No encontrada
A42: 37 | B42: Si | E42: Sin información | F42: Yalo | G42: Canal conversacional WhatsApp para atención al aprendedor y prospecto | H42: Sin información | I42: Sin información | J42: Sin información | K42: Blanca Mata (confirmar) | L42: Sin información | M42: Sin información | N42: Sin información | O42: Sin información | P42: Yalo | Q42: Commercial Off-the-Shelf | R42: Cloud-SaaS | S42: Yalo (plataforma conversacional WhatsApp) | T42: Sin información | U42: Sin información | V42: Sin información | W42: Sin información | X42: Sin información | Y42: Sin información | Z42: Sin información | AA42: 0 | AB42: 0 | AC42: 0 | AD42: 0 | AE42: Medium | AF42: 3 | AH42: =IF(AND(AF42>=3,AG42>=3),"Invest",IF(AND(AF42>=3,AG42<3),"Migrate",IF(AND(AF42<3,AG42>=3),"Tolerate","Eliminate"))) -> Migrate | AI42: Sin información | AJ42: Sin información | AK42: Active | AL42: Sin información | AM42: Sin información | AN42: Sin información | AO42: Canal conversacional WhatsApp para atención al aprendedor y prospecto | AP42: Transversal | AQ42: 3 | AR42: No se encontró carpeta correspondiente en el índice de SharePoint | AS42: No encontrada
A43: 38 | E43: 0027-HTI-018-CRMC | F43: Tuvis | G43: Bridge entre WhatsApp/Yalo y Salesforce para trazabilidad comercial | H43: 16. Línea de Servicio | I43: HT04. Salesforce | J43: Juan (solo nombre de pila; fuente: Correspondencia_Aplicaciones_APM_vs_Habilitadores.xlsx) | K43: G Garcia Sigg | L43: blancamata@tec.mx | M43: g.garcia.sigg@tec.mx | N43: aaron.urbina@tec.mx | O43: orlando.salinas@tec.mx | P43: Tuvis | Q43: Commercial Off-the-Shelf | R43: Cloud-SaaS | S43: Tuvis (mensajería integrada Salesforce) | T43: https://micrmtec.lightning.force.com/lightning | U43: Sin información | V43: Sin información | W43: Sin información | X43: Sin información | Y43: Sin información | Z43: Sin información | AA43: 0 | AB43: 0 | AC43: 0 | AD43: 0 | AE43: Medium | AF43: 3 | AH43: =IF(AND(AF43>=3,AG43>=3),"Invest",IF(AND(AF43>=3,AG43<3),"Migrate",IF(AND(AF43<3,AG43>=3),"Tolerate","Eliminate"))) -> Migrate | AI43: Sin información | AJ43: Sin información | AK43: Active | AL43: Sin información | AM43: Confidential | AN43: Sin información | AO43: Bridge entre WhatsApp/Yalo y Salesforce para trazabilidad comercial | AP43: Transversal | AQ43: 3 | AR43: No se encontró carpeta correspondiente en el índice de SharePoint | AS43: No encontrada
A44: 39 | B44: Si | E44: 5153-VPA-001-TRXC | F44: Pulsar | G44: Bus de eventos y mensajería para personalización, recomendaciones y orquestación entre habilitadores | H44: Sin información | I44: Sin información | J44: Juan (solo nombre de pila; fuente: Correspondencia_Aplicaciones_APM_vs_Habilitadores.xlsx) | K44: ctvalenzuela@tec.mx | L44: ctvalenzuela@tec.mx | M44: ctvalenzuela@tec.mx | N44: ctvalenzuela@tec.mx -> se pasará a Uman Diez | O44: ctvalenzuela@tec.mx -> se pasará a Uman Diez | P44: Apache Pulsar (mensajería de eventos) | Q44: Commercial Off-the-Shelf | R44: Hybrid | S44: Apache Pulsar (mensajería de eventos) | T44: Sin información | U44: Sin información | V44: Sin información | W44: Sin información | X44: Sin información | Y44: Sin información | Z44: Sin información | AA44: 0 | AB44: 0 | AC44: 0 | AD44: 0 | AE44: High | AF44: 4 | AH44: =IF(AND(AF44>=3,AG44>=3),"Invest",IF(AND(AF44>=3,AG44<3),"Migrate",IF(AND(AF44<3,AG44>=3),"Tolerate","Eliminate"))) -> Migrate | AI44: Sin información | AJ44: Sin información | AK44: Suspended | AL44: 9 hops documentados como transportador/orquestador: SEA↔Pulsar (SPD-001, SOE-001/003, SPV-001), Pulsar→Drupal (SPD-002, upsert JSON:API de programas), Pulsar→Salesforce (SOE-002/004, upsert Account y Program Plan), Pulsar→VTEX (SPV-002/003/004/005/006, Catalog + Pricing API), Pulsar↔Accredible (GI-004, emisión de badges), Pulsar→MDM/OpenText (GI-003, pendiente de definición de API), Pulsar→Portal Unificado (GI-005), LXP(Cypher/TLG)→Pulsar (GI-001, evento asíncrono). Fuente: carpetas Integraciones/MVP1/Flujo de actualización de programas y Acreditación y credencialización. | AM44: Sin información | AN44: Sin información | AO44: Bus de eventos y mensajería para personalización, recomendaciones y orquestación entre habilitadores | AP44: Transversal | AQ44: 4 | AR44: Flujo de actualización de programas (JOB-012 SEA-Pulsar-*) | AS44: Confirmada
A45: 40 | E45: Sin información | F45: Algolia | G45: Motor de búsqueda para oferta y contenidos en portales VPAF | H45: Sin información | I45: Sin información | J45: Sin información | K45: Sin información | L45: Sin información | M45: Sin información | N45: Sin información | O45: Sin información | P45: Algolia (motor de búsqueda) | Q45: Commercial Off-the-Shelf | R45: Cloud-SaaS | S45: Algolia (motor de búsqueda) | T45: Sin información | U45: Sin información | V45: Sin información | W45: Sin información | X45: Sin información | Y45: Sin información | Z45: Sin información | AA45: 0 | AB45: 0 | AC45: 0 | AD45: 0 | AE45: Medium | AF45: 3 | AH45: =IF(AND(AF45>=3,AG45>=3),"Invest",IF(AND(AF45>=3,AG45<3),"Migrate",IF(AND(AF45<3,AG45>=3),"Tolerate","Eliminate"))) -> Migrate | AI45: Sin información | AJ45: Sin información | AK45: Active | AL45: Sin información | AM45: Sin información | AN45: Sin información | AO45: Motor de búsqueda para oferta y contenidos en portales VPAF | AP45: Transversal | AQ45: 3 | AR45: Flujo de búsqueda de productos (incluye DIR-011 Portal-Search Bar) | AS45: Parcial / relacionada
A46: 41 | B46: Si | E46: 0253-HTI-001-BOTC | F46: TEC.bot | G46: Asistente virtual del Portal Unificado; tratamiento automatizado | H46: 09. Inteligencia Artificial | I46: AI01. TEC.bot | J46: gilberto.bastidas@tec.mx | K46: rrico@tec.mx (Sugerencia Miguel Burgoin) t-romangonzalez@itesm.mx CORRECCIÓN IMPORTANTE (sesión S-047, 15-sep-2026, posterior a S-046): se confirmó que "TEC.bot" (este habilitador institucional, registrado en este inventario, responsable histórico Manuel Terán) y "TEC 360 (Agente 360)" (proyecto nuevo liderado por Rafael Rico Camacho, con infraestructura y arquitectura propias) son DOS HABILITADORES DISTINTOS, aunque comparten antecedentes y tecnología similar y la denominación "TEC Bot" se sigue usando de forma informal para ambos. La sugerencia de la sesión anterior (S-046, 14-sep-2026) de cambiar el responsable técnico de este habilitador a Rafael Rico Camacho correspondía en realidad al proyecto TEC 360, NO a este TEC.bot institucional — no debe aplicarse ese cambio aquí. Responsable técnico institucional confirmado de TEC.bot: Manuel Terán. Se mantiene sin cambio la referencia previa a Thia Román González (t-romangonzalez@itesm.mx). | L46: Miguel Burgoin / Rafa Velez Confirmado en sesión S-046 (14-sep-2026): Miguel Ángel Burgoin Carrera (miguel.burgoin@tec.mx) es el usuario funcional principal y Gerente de Producto de TEC.bot (requerimientos, prioridades funcionales, pruebas, base de conocimiento) — no es el dueño técnico de la plataforma. | M46: rrico@tec.mx | N46: Uman Diez | O46: Uman Diez | P46: Agente conversacional con IA generativa Desarrollo de este habilitador a cargo del proveedor Movit (confirmado en sesión S-046, 14-sep-2026). | Q46: Custom Development | R46: Cloud-SaaS | S46: Agente conversacional con IA generativa | T46: Sin información | U46: Sin información | V46: Sin información | W46: Sin información | X46: Sin información | Y46: Sin información | Z46: Sin información | AA46: 0 | AB46: 0 | AC46: 0 | AD46: 0 | AE46: High | AF46: 4 | AH46: =IF(AND(AF46>=3,AG46>=3),"Invest",IF(AND(AF46>=3,AG46<3),"Migrate",IF(AND(AF46<3,AG46>=3),"Tolerate","Eliminate"))) -> Migrate | AI46: Sin información | AJ46: Sin información | AK46: Active Confirmado en sesión S-046 (14-sep-2026): TEC.bot aún se encuentra en fase de construcción y NO opera en producción; se esperaba, a esa fecha, comenzar a visualizarse en ambientes de prueba aproximadamente un mes después. Desarrollo a cargo del proveedor Movit — pendiente validar con Movit la documentación técnica/funcional contemplada en los entregables del proyecto. | AL46: 2 confirmadas: (1) INT-R2-001 Portal Único ↔ TEC.bot — inicialización del widget vía Direct Line Token, bidireccional; (2) INT-R2-002 TEC.bot → ServiceNow — creación de ticket (Table API REST) como único mecanismo de escalación cuando el árbol de decisiones no resuelve la solicitud (nivel N0). Fuente: carpeta "Agente conversacional tecbot - Flujo de soporte a usuarios". | AM46: Confidential | AN46: Sin información | AO46: Asistente virtual del Portal Unificado; tratamiento automatizado | AP46: Transversal | AQ46: 4 | AR46: Agente conversacional tecbot - Flujo de soporte a usuarios | AS46: Confirmada
A47: 42 | E47: 5149-VPA-001-BIPC | F47: Buscador / Search Bar | G47: Experiencia de búsqueda unificada en Portal Unificado | H47: Sin información | I47: Sin información | J47: nlopeznegrete@tec.mx | K47: rrico@tec.mx | L47: rrico@tec.mx | M47: rrico@tec.mx | N47: Sin información | O47: Sin información | P47: Frontend de búsqueda (integra Algolia y TEC.gpt) | Q47: Commercial Off-the-Shelf | R47: Cloud-SaaS | S47: Frontend de búsqueda (integra Algolia y TEC.gpt) | T47: Sin información | U47: Sin información | V47: Sin información | W47: Sin información | X47: Sin información | Y47: Sin información | Z47: Sin información | AA47: 0 | AB47: 0 | AC47: 0 | AD47: 0 | AE47: Medium | AF47: 3 | AH47: =IF(AND(AF47>=3,AG47>=3),"Invest",IF(AND(AF47>=3,AG47<3),"Migrate",IF(AND(AF47<3,AG47>=3),"Tolerate","Eliminate"))) -> Migrate | AI47: Sin información | AJ47: Sin información | AK47: Active | AL47: Sin información | AM47: Sin información | AN47: Sin información | AO47: Experiencia de búsqueda unificada en Portal Unificado ⚠ Verificar: ID Habilitador también asignado a fila 10 ("Sistema de Rúbricas / Perfilador"). | AP47: Transversal | AQ47: 3 | AR47: DIR-011 - Portal-Search Bar | AS47: Confirmada
A48: 43 | B48: Si | E48: 0530-HTI-001-DWPC | F48: Portal Unificado | G48: Front único del aprendedor; orquesta navegación entre habilitadores | H48: 11. Distribución Digital | I48: DD01. TEC.portal | J48: omar.jimenez@tec.mx | K48: jirodrig@tec.mx | L48: jdcantu@tec.mx | M48: jirodrig@tec.mx | N48: Diana Dolores Morón González (diana.moron@tec.mx) — contacto principal identificado del lado del Portal en la sesión de contexto S-038 (04/09/2026). Pendiente confirmar si corresponde formalmente al rol de Responsable de operación o a otro rol (funcional/negocio). | O48: Arturo Rodríguez (Líder de Soporte — OLA "CMS Drupal – Portal Unificado", 17-ago-2026) | P48: Drupal | Q48: Commercial Off-the-Shelf | R48: Cloud-SaaS | S48: Frontend (Next.js) + Drupal CMS | T48: Sin información | U48: Sin información | V48: https://wa-pprd-portal-next-front.azurewebsites.net/ (verificación del portal en ambiente de Calidad/QA — OLA "CMS Drupal – Portal Unificado", 17-ago-2026) | W48: Sin información | X48: Sin información | Y48: Sin información | Z48: Sin información | AA48: 0 | AB48: 0 | AC48: 0 | AD48: 0 | AE48: Mission Critical | AF48: 5 | AH48: =IF(AND(AF48>=3,AG48>=3),"Invest",IF(AND(AF48>=3,AG48<3),"Migrate",IF(AND(AF48<3,AG48>=3),"Tolerate","Eliminate"))) -> Migrate | AI48: Sin información | AJ48: Sin información | AK48: Active | AL48: Sin información Pendiente de compartir (sesión S-038, 04-sep-2026): las carpetas "Moto Support" y "Moto Operation" utilizadas actualmente por el equipo del Portal, referidas por Erika Ortiz Hernández (Consultor Externo ectotec) como fuente adicional de documentación operativa. | AM48: Sin información | AN48: Sin información | AO48: Front único del aprendedor; orquesta navegación entre habilitadores | AP48: Transversal | AQ48: 5 | AR48: Integración Portal-Drupal - DIR-000 | AS48: Parcial / relacionada
A49: 44 | B49: Si | E49: 0601-HTI-003-DWPC | F49: Drupal CMS | G49: CMS para contenidos del Portal Unificado y sitios institucionales | H49: 11. Distribución Digital | I49: DD03. TEC.sites | J49: Diana Morón — PO citada en integración Drupal CMS → Portal | K49: Bernardo Duran | L49: rafael.velez@tec.mx / cfrancor@tec.mx | M49: Diana Morón | N49: Uman Diez | O49: Uman Diez | P49: Drupal | Q49: Commercial Off-the-Shelf | R49: Cloud-SaaS | S49: Drupal (gestión central Tec) | T49: Sin información | U49: Sin información | V49: https://test-cms.tec360.com/ (ambiente de Calidad/QA del CMS, acceso protegido por VPN TEC obligatoria — OLA "CMS Drupal – Portal Unificado", 17-ago-2026) | W49: Sin información | X49: Sin información | Y49: Sin información | Z49: Sin información | AA49: 0 | AB49: 0 | AC49: 0 | AD49: 0 | AE49: High | AF49: 4 | AH49: =IF(AND(AF49>=3,AG49>=3),"Invest",IF(AND(AF49>=3,AG49<3),"Migrate",IF(AND(AF49<3,AG49>=3),"Tolerate","Eliminate"))) -> Migrate | AI49: Sin información | AJ49: Sin información | AK49: Active | AL49: 2 confirmadas: (1) INT-R1-001 Drupal → BFF del Portal Unificado (GraphQL, read-only, contenido editorial: cursos, páginas institucionales, banners); (2) SPD-002 Pulsar → Drupal (JSON:API, upsert de nodo "programa" por sincronización con SEA vía SPD-001). Fuente: carpetas "Integración Portal-Drupal - DIR-000" y "JOB-012 - SEA-Pulsar-Drupal". | AM49: Sin información | AN49: Sin información | AO49: CMS para contenidos del Portal Unificado y sitios institucionales | AP49: Transversal | AQ49: 4 | AR49: Integración Portal-Drupal - DIR-000 | AS49: Confirmada
A50: 45 | B50: Si | E50: 5149-VPA-002-IAMC | F50: OpenText Access Manager (NAM) | G50: Gestión de identidad federada (SAML 2.0); integración con identidad institucional | H50: Sin información | I50: Sin información | J50: Juan (solo nombre de pila; fuente: Correspondencia_Aplicaciones_APM_vs_Habilitadores.xlsx) | K50: Arturo A | L50: arturo.a@tec.mx | M50: arturo.a@tec.mx | N50: alma.ortizh@tec.mx | O50: alma.ortizh@tec.mx | P50: OpenText | Q50: Commercial Off-the-Shelf | R50: Cloud-SaaS | S50: OpenText NAM (identidad federada) | T50: Sin información | U50: Sin información | V50: Sin información | W50: Sin información | X50: Sin información | Y50: Sin información | Z50: Sin información | AA50: 0 | AB50: 0 | AC50: 0 | AD50: 0 | AE50: Mission Critical | AF50: 5 | AH50: =IF(AND(AF50>=3,AG50>=3),"Invest",IF(AND(AF50>=3,AG50<3),"Migrate",IF(AND(AF50<3,AG50>=3),"Tolerate","Eliminate"))) -> Migrate | AI50: Sin información | AJ50: Sin información | AK50: Active | AL50: 3 confirmadas por regla de negocio / estándar técnico (segunda pasada, 10-sep-2026): (1) NAM ⇄ Entra/Azure AD — reutilización de identidad institucional para Comunidad Tec (Matriz de Reglas de Negocio Identidad Digital VPAF, regla RN-069); (2) TLG ↔ NAM — SSO institucional vía OIDC/OAuth2, en preparación, contrato de autenticación aún no habilitado en DEVL al 01-jul-2026 ("Premisas de Integración OIDC · TLG" v1.0); (3) NAM ⇄ Habilitadores federados del ecosistema VPAF (genérico, SAML 2.0 u OIDC/OAuth2 según habilitador — reglas RN-073 a RN-076). No se cuenta con un inventario exhaustivo de todos los habilitadores ya federados. | AM50: Confidential | AN50: Sin información | AO50: Gestión de identidad federada (SAML 2.0); integración con identidad institucional | AP50: Transversal | AQ50: 5 | AR50: Identidad Digital (carpeta de estrategia, roles/permisos, identidad federada) | AS50: Parcial / relacionada
A51: 46 | B51: Si | E51: Sin información | F51: OpenPay | G51: Pasarela de pagos para transacciones de e-commerce vía VTEX | H51: Sin información | I51: Sin información | J51: Sin información | K51: Equipo Central* (Validar con Daniel Perez y Flor Esquivel) | L51: Flor Esquivel | M51: Flor Esquivel | N51: Equipo Central* (Validar con Daniel Perez y Flor Esquivel) | O51: Equipo Central* (Validar con Daniel Perez y Flor Esquivel) | P51: OpenPay | Q51: SaaS | R51: Cloud-SaaS | S51: OpenPay (pasarela de pagos) | T51: Sin información | U51: Sin información | V51: Sin información | W51: Sin información | X51: Sin información | Y51: Sin información | Z51: Sin información | AA51: 0 | AB51: 0 | AC51: 0 | AD51: 0 | AE51: Mission Critical | AF51: 5 | AH51: =IF(AND(AF51>=3,AG51>=3),"Invest",IF(AND(AF51>=3,AG51<3),"Migrate",IF(AND(AF51<3,AG51>=3),"Tolerate","Eliminate"))) -> Migrate | AI51: Sin información | AJ51: Sin información | AK51: Active | AL51: 1 posible, no confirmada: dentro del checkout nativo de VTEX (DIR-001-04, PCHK) se configuran 7 métodos de pago como "Payment Gateways" en VTEX Admin (tarjeta débito/crédito, PayPal, FlyWire, Ficha de Depósito Nacional, banca electrónica, OXXO Pay, SPEI), cada uno gestionado por el equipo VTEX TEC. La ficha de integración NO nombra explícitamente a OpenPay como el gateway subyacente de ninguno de esos métodos — pendiente de confirmar con el equipo VTEX TEC cuál proveedor opera cada uno. | AM51: Sin información | AN51: Sin información | AO51: Pasarela de pagos para transacciones de e-commerce vía VTEX | AP51: Transversal | AQ51: 5 | AR51: Flujo de compra de productos (incluye checkout VTEX + validación de cupo) | AS51: Parcial / relacionada
A52: 47 | B52: Si | E52: 0490-HTI-001-TRXC | F52: VTEX | G52: Plataforma de e-commerce para venta de productos educativos digitales | H52: 04. Finanzas | I52: FNC02. Facturación | J52: Toño (solo nombre de pila; fuente: Correspondencia_Aplicaciones_APM_vs_Habilitadores.xlsx) Dato de contrato (Template contratos_11Sep26_V1.xlsx): Business Owner = Tania Nohemi Villa Silva; Vendor = VTEX MEXICO SOLUCIONES EN ECOMMERCE S. de R.L. de C.V.; Contract Administrator = Juan Alonso Valenzuela Rodríguez; Approver = Carmen Isabel Reyes Peraza. Pendiente reconciliar con el nombre "Toño" ya registrado como dueño de negocio desde otra fuente. | K52: jebreyes@tec.mx Contactos adicionales identificados en sesión S-035 (02-sep-2026): María de Lourdes Ayala Mercado (lourdes.ayala@tec.mx) y Remigio Martínez Osorio (remigio.m@tec.mx) — documentación de VTEX pendiente de ser compartida por su equipo (compromiso registrado en la minuta de esa sesión, aún no cumplido a la fecha de esta pasada). | L52: Fernando Moreira | M52: jebreyes@tec.mx | N52: fmoreira@tec.mx | O52: colivar@tec.mx | P52: VTEX | Q52: Commercial Off-the-Shelf | R52: Cloud-SaaS | S52: VTEX (plataforma e-commerce) | T52: https://market.tec.mx/login?samltec | U52: Sin información | V52: Sin información | W52: Sin información | X52: Sin información | Y52: Sin información | Z52: Ambiente QA (no producción): 23 roles definidos (Owner Admin Super, OMS - Full access, Finance, Checkout Admin, Tec QA, Logistics - Full access, etc.) y ~35 usuarios con roles asignados, incluyendo cuentas del proveedor @wallia.io con permisos de Owner/Admin (fuente: 'Roles y Usuarios VTEX - Ambiente QA.xlsx'). No es una cifra de usuarios activos en producción. | AA52: 0 | AB52: 0 | AC52: 0 | AD52: 0 | AE52: Mission Critical | AF52: 5 | AH52: =IF(AND(AF52>=3,AG52>=3),"Invest",IF(AND(AF52>=3,AG52<3),"Migrate",IF(AND(AF52<3,AG52>=3),"Tolerate","Eliminate"))) -> Migrate | AI52: Sin información | AJ52: Sin información | AK52: Active | AL52: Sin información | AM52: Sin información | AN52: Sin información | AO52: Plataforma de e-commerce para venta de productos educativos digitales ⚠ Verificar: ID Habilitador también asignado a fila 41 ("Market Tec"). | AP52: Transversal | AQ52: 5 | AR52: DIR-012 - Portal-VTEX IS (ver también DIR-001-01..04 y JOB-012-Pulsar-VTEX) | AS52: Confirmada
A53: 48 | E53: 0024-HTI-001-CRMC | F53: Marketing Cloud | G53: Automatización de marketing transaccional y campañas avanzadas | H53: 06. Proyección y Vinculación | I53: MKT03. Promoción | J53: Toño (solo nombre de pila; fuente: Correspondencia_Aplicaciones_APM_vs_Habilitadores.xlsx) | K53: Rafael Robles | L53: diana.gzz@tec.mx | M53: rafael.robles@tec.mx | N53: jesus.rendon@tec.mx | O53: oscar.rdz@tec.mx | P53: Salesforce | Q53: Commercial Off-the-Shelf | R53: Cloud-SaaS | S53: Salesforce Marketing Cloud | T53: Sin información | U53: Sin información | V53: Sin información | W53: Sin información | X53: Sin información | Y53: Sin información | Z53: Sin información | AA53: 0 | AB53: 0 | AC53: 0 | AD53: 0 | AE53: Medium | AF53: 3 | AH53: =IF(AND(AF53>=3,AG53>=3),"Invest",IF(AND(AF53>=3,AG53<3),"Migrate",IF(AND(AF53<3,AG53>=3),"Tolerate","Eliminate"))) -> Migrate | AI53: Sin información | AJ53: Sin información | AK53: Active | AL53: Sin información | AM53: Sin información | AN53: Sin información | AO53: Automatización de marketing transaccional y campañas avanzadas | AP53: Transversal | AQ53: 3 | AR53: No se encontró carpeta correspondiente en el índice de SharePoint | AS53: No encontrada
A54: 49 | B54: Si | E54: 5039-HTI-001-BIST | F54: FUD (DWH) | G54: Fuente Única de Datos: repositorio analítico unificado; en Fase 1 de implementación | H54: 10. Plataforma de Datos | I54: DP01. TEC.data | J54: Salvador Adrián Tijerina Dávila (satijerinad@tec.mx) concentra actualmente la documentación, la definición funcional y la coordinación de la implementación de FUD (sesión S-048, 15/09/2026) — iniciales 'SAT' ya reflejadas en Responsable funcional. Aún NO hay un Product Owner formalmente designado; queda pendiente definir explícitamente los roles de Product Owner, Responsable Funcional y Responsable Técnico como distintos entre sí. | K54: malcala@tec.mx | L54: SAT | M54: malcala@tec.mx | N54: Equipo Central* (Validar) | O54: Equipo Central* (Validar) | P54: Data warehouse central (en construcción) | Q54: Custom Development | R54: Sin información | S54: Data warehouse central (en construcción) | T54: Sin información | U54: Sin información | V54: Sin información | W54: Sin información | X54: Sin información | Y54: Sin información | Z54: Sin información | AA54: 0 | AB54: 0 | AC54: 0 | AD54: 0 | AE54: Mission Critical | AF54: 5 | AH54: =IF(AND(AF54>=3,AG54>=3),"Invest",IF(AND(AF54>=3,AG54<3),"Migrate",IF(AND(AF54<3,AG54>=3),"Tolerate","Eliminate"))) -> Migrate | AI54: Sin información | AJ54: Sin información | AK54: Active | AL54: 17 fuentes de datos programadas para integrar en el roadmap MVP1 (abr–oct 2026): SEA-SIS, Cypher Learning, TLG, MDM, Banner (Tec y UTM), SAP/HANA, Interfactura, Portal Unificado (Tecnográficos y Compra y Pago), VTEX (eCommerce), Salesforce CRM, Qualtrics, tec.feedback, PASE, Buscador/Search Bar, TEC.bot VPAF — habilitando 11 modelos de datos (Persona, Gestión del Aprendizaje, Ingresos, Financiero, Tecnográficos, Compra y Pago, Comercial U4P, Telemetría, Encuestas, NPS, Expertos). | AM54: Sin información | AN54: Sin información | AO54: Fuente Única de Datos: repositorio analítico unificado; en Fase 1 de implementación Aclaración (sesión S-048, 15-sep-2026): FUD es el nombre del PROYECTO de habilitación del Data Warehouse institucional para la VPAF, no un producto independiente; debe alinearse con la arquitectura de datos corporativa (equipos centrales de datos: Ma. Elizabeth Alcalá Flores malcala@tec.mx, Lucero Mayela Sotomayor Ruiz lucero_sotomayor@tec.mx). Existe un modelo centralizado de operación institucional para el Data Warehouse (DBAs, plataformas de integración, virtualización, Power BI, soporte BI), pero el soporte operativo específico de FUD dentro de la VPAF aún no está definido; los roles de Product Owner, Responsable Funcional y Responsable Técnico, hoy concentrados principalmente en Salvador Adrián Tijerina Dávila, quedan pendientes de formalizar como distintos entre sí. | AP54: Transversal | AQ54: 5 | AR54: FUD (Transformación / Ecosistema Digital del Futuro) | AS54: Confirmada
A55: 50 | F55: Middleware B2C | T55: Sin información | U55: Sin información | V55: Sin información | W55: Sin información | X55: Sin información | Y55: Sin información | Z55: Sin información | AA55: 0 | AB55: 0 | AC55: 0 | AE55: Mission Critical | AH55: =IF(AND(AF55>=3,AG55>=3),"Invest",IF(AND(AF55>=3,AG55<3),"Migrate",IF(AND(AF55<3,AG55>=3),"Tolerate","Eliminate"))) -> Eliminate | AI55: Sin información | AJ55: Sin información | AK55: Active | AL55: Sin información | AM55: Sin información | AN55: Sin información
A56: 51 | F56: Middleware B2B | G56: - | K56: Victor Rafael Tena | L56: Larisa Díaz / Ana Karen Jimenez | M56: victor.tena@tec.mx | N56: victor.tena@tec.mx | O56: victor.tena@tec.mx | T56: Sin información | U56: Sin información | V56: Sin información | W56: Sin información | X56: Sin información | Y56: Sin información | Z56: Sin información | AA56: 0 | AB56: 0 | AC56: 0 | AE56: Mission Critical | AH56: =IF(AND(AF56>=3,AG56>=3),"Invest",IF(AND(AF56>=3,AG56<3),"Migrate",IF(AND(AF56<3,AG56>=3),"Tolerate","Eliminate"))) -> Eliminate | AI56: Sin información | AJ56: Sin información | AK56: Active | AL56: Sin información | AM56: Sin información | AN56: Sin información | AO56: Nota (10-sep-2026, fuente Repositorio TD-Ecosistema Digital VPAF): no se encontró ningún habilitador con el nombre exacto "Middleware B2B" en el repositorio. Candidatos posibles, sin confirmar: (1) la integración PGL-001 (carpeta Integraciones/MVP1/Registro de Leads B2B - Salesforce/PGL Generación Automática de Lead.docx, jul-2026) — el Portal Unificado (BFF) envía un lead B2B directo al CRM Salesforce vía PATCH /sobjects/Lead/{ExternalIdField} (Upsert síncrono, OAuth 2.0 JWT Bearer); es un hop directo Portal→Salesforce, no un middleware intermedio, así que probablemente no es lo mismo. (2) menciones sueltas a "Middleware 26" y "Middleware ESB IBM" en Integraciones/MVP1/20260408 Documento Integraciones verano publica_v1.pdf, como capas de integración legadas genéricas (Banner, SAP/HANA, Gestor de pagos, Interfactura) — sin evidencia textual de que se relacionen con B2B específicamente. Pendiente confirmar con el equipo si "Middleware B2B" corresponde a alguno de estos. | AP56: VEC | AR56: Búsqueda exhaustiva en Repositorio TD-Ecosistema Digital VPAF (wiki completa + Integraciones/MVP1 + MVP2 + gobierno de aplicaciones/aplicativos/datos + identidad digital); no se encontró el nombre exacto, solo candidatos relacionados sin confirmar (ver Notas) | AS56: Parcial / relacionada
A57: 52 | B57: Si | F57: Sistema de ordenes internas B2B | T57: Sin información | U57: Sin información | V57: Sin información | W57: Sin información | X57: Sin información | Y57: Sin información | Z57: Sin información | AA57: 0 | AB57: 0 | AC57: 0 | AE57: Mission Critical | AH57: =IF(AND(AF57>=3,AG57>=3),"Invest",IF(AND(AF57>=3,AG57<3),"Migrate",IF(AND(AF57<3,AG57>=3),"Tolerate","Eliminate"))) -> Eliminate | AI57: Sin información | AJ57: Sin información | AK57: Active | AL57: Sin información | AM57: Sin información | AN57: Sin información | AR57: Búsqueda exhaustiva en Repositorio TD-Ecosistema Digital VPAF el 10-sep-2026 (wiki institucional completa — 224 páginas — más Integraciones/MVP1, MVP2, gobierno de aplicaciones/aplicativos/datos, identidad digital, catálogos y documentos adicionales); no se encontró ninguna mención de este habilitador con ese nombre ni variantes cercanas | AS57: No encontrada
A58: 53 | F58: Speed2Lead (Asignator) | T58: Sin información | U58: Sin información | V58: Sin información | W58: Sin información | X58: Sin información | Y58: Sin información | Z58: Sin información | AA58: 0 | AB58: 0 | AC58: 0 | AE58: Mission Critical | AH58: =IF(AND(AF58>=3,AG58>=3),"Invest",IF(AND(AF58>=3,AG58<3),"Migrate",IF(AND(AF58<3,AG58>=3),"Tolerate","Eliminate"))) -> Eliminate | AI58: Sin información | AJ58: Sin información | AK58: Active | AL58: Sin información | AM58: Sin información | AN58: Sin información | AP58: VEC | AR58: Búsqueda exhaustiva en Repositorio TD-Ecosistema Digital VPAF el 10-sep-2026 (wiki institucional completa — 224 páginas — más Integraciones/MVP1, MVP2, gobierno de aplicaciones/aplicativos/datos, identidad digital, catálogos y documentos adicionales); no se encontró ninguna mención de este habilitador con ese nombre ni variantes cercanas | AS58: No encontrada
A59: 54 | F59: Monitor de colorimetria | T59: Sin información | U59: Sin información | V59: Sin información | W59: Sin información | X59: Sin información | Y59: Sin información | Z59: Sin información | AA59: 0 | AB59: 0 | AC59: 0 | AE59: Mission Critical | AH59: =IF(AND(AF59>=3,AG59>=3),"Invest",IF(AND(AF59>=3,AG59<3),"Migrate",IF(AND(AF59<3,AG59>=3),"Tolerate","Eliminate"))) -> Eliminate | AI59: Sin información | AJ59: Sin información | AK59: Active | AL59: Sin información | AM59: Sin información | AN59: Sin información | AP59: VEC | AR59: Búsqueda exhaustiva en Repositorio TD-Ecosistema Digital VPAF el 10-sep-2026 (wiki institucional completa — 224 páginas — más Integraciones/MVP1, MVP2, gobierno de aplicaciones/aplicativos/datos, identidad digital, catálogos y documentos adicionales); no se encontró ninguna mención de este habilitador con ese nombre ni variantes cercanas | AS59: No encontrada
A60: 55 | F60: Enrutador de correos | T60: Sin información | U60: Sin información | V60: Sin información | W60: Sin información | X60: Sin información | Y60: Sin información | Z60: Sin información | AA60: 0 | AB60: 0 | AC60: 0 | AE60: Mission Critical | AH60: =IF(AND(AF60>=3,AG60>=3),"Invest",IF(AND(AF60>=3,AG60<3),"Migrate",IF(AND(AF60<3,AG60>=3),"Tolerate","Eliminate"))) -> Eliminate | AI60: Sin información | AJ60: Sin información | AK60: Active | AL60: Sin información | AM60: Sin información | AN60: Sin información | AO60: Nota (10-sep-2026, fuente Repositorio TD-Ecosistema Digital VPAF): no se encontró el nombre exacto "Enrutador de correos", pero el componente que funcionalmente actúa como enrutador/relay de correo institucional es el SMTP Gateway (FUD/Pages/SMTP-Gateway.html, dueño Alejandro Guajardo Moreno — Infraestructura TI, publicado 5-abr-2022): "la puerta de salida hacia el mundo de todos los correos transaccionales que generan nuestros sistemas" — solo correo transaccional (facturas, notificaciones, calificaciones), envío masivo/marketing prohibido, solo sistemas dentro de los CPD del Tec (servicios cloud externos como Success Factors/Concur/Coupa no se conectan ahí), remitente obligatorio @servicios.itesm.mx, solicitud de alta vía doi.correo@itesm.mx. Se deja como candidato sin confirmar — no se llenaron los campos principales (Descripción, Responsables, etc.) hasta confirmar con el equipo si es el mismo habilitador. | AP60: VEC | AR60: Repositorio TD-Ecosistema Digital VPAF/FUD/Pages/SMTP-Gateway.html (candidato relacionado, sin confirmar) | AS60: Parcial / relacionada
A61: 56 | F61: Prefect (Orquestador de tableros) | T61: Sin información | U61: Sin información | V61: Sin información | W61: Sin información | X61: Sin información | Y61: Sin información | Z61: Sin información | AA61: 0 | AB61: 0 | AC61: 0 | AE61: Mission Critical | AH61: =IF(AND(AF61>=3,AG61>=3),"Invest",IF(AND(AF61>=3,AG61<3),"Migrate",IF(AND(AF61<3,AG61>=3),"Tolerate","Eliminate"))) -> Eliminate | AI61: Sin información | AJ61: Sin información | AK61: Active | AL61: Sin información | AM61: Sin información | AN61: Sin información | AP61: VEC | AR61: Búsqueda exhaustiva en Repositorio TD-Ecosistema Digital VPAF el 10-sep-2026 (wiki institucional completa — 224 páginas — más Integraciones/MVP1, MVP2, gobierno de aplicaciones/aplicativos/datos, identidad digital, catálogos y documentos adicionales); no se encontró ninguna mención de este habilitador con ese nombre ni variantes cercanas | AS61: No encontrada
A62: 57 | F62: Contenedora de Skills (Orquestador de Skills) | T62: Sin información | U62: Sin información | V62: Sin información | W62: Sin información | X62: Sin información | Y62: Sin información | Z62: Sin información | AA62: 0 | AB62: 0 | AC62: 0 | AE62: Mission Critical | AH62: =IF(AND(AF62>=3,AG62>=3),"Invest",IF(AND(AF62>=3,AG62<3),"Migrate",IF(AND(AF62<3,AG62>=3),"Tolerate","Eliminate"))) -> Eliminate | AI62: Sin información | AJ62: Sin información | AK62: Active | AL62: Sin información | AM62: Sin información | AN62: Sin información | AO62: Nota (10-sep-2026, fuente Repositorio TD-Ecosistema Digital VPAF): no se encontró el nombre exacto "Contenedora de Skills"/"Orquestador de Skills", pero FUD/Pages/Arquitectura-de-componentes-de-IA.html (autor Alfonso Jesús Treviño Cantú) describe que Tec.Gpt "cuenta con dos portales propios: uno para realizar consultas y otro para crear skills, entendiéndose por skill una habilidad o rutina repetitiva que queremos invocar frecuentemente [...] de manera rápida y simplificada" — el prompt se traduce a vectores vía embeddings (API de OpenAI) y se cachean temporalmente (no persistente) en REDIS, sobre Azure/OpenAI. FUD/Pages/Tec.gpt.html confirma el dueño: Manuel Terán Melgarejo, Gerencia del Centro de Arquitectura y Habilitación de Inteligencia Artificial, publicado 17-abr-2023. Se deja como candidato sin confirmar — no se llenaron los campos principales hasta confirmar con el equipo si "Contenedora de Skills" es este portal de Tec.Gpt o un componente distinto. | AP62: VEC | AR62: Repositorio TD-Ecosistema Digital VPAF/FUD/Pages/Arquitectura-de-componentes-de-IA.html y Tec.gpt.html (candidato relacionado, sin confirmar) | AS62: Parcial / relacionada
A63: 58 | F63: Formateador de semblanzas PASE | T63: Sin información | U63: Sin información | V63: Sin información | W63: Sin información | X63: Sin información | Y63: Sin información | Z63: Sin información | AA63: 0 | AB63: 0 | AC63: 0 | AE63: Mission Critical | AH63: =IF(AND(AF63>=3,AG63>=3),"Invest",IF(AND(AF63>=3,AG63<3),"Migrate",IF(AND(AF63<3,AG63>=3),"Tolerate","Eliminate"))) -> Eliminate | AI63: Sin información | AJ63: Sin información | AK63: Active | AL63: Sin información | AM63: Sin información | AN63: Sin información | AP63: VEC | AR63: Búsqueda exhaustiva en Repositorio TD-Ecosistema Digital VPAF el 10-sep-2026 (wiki institucional completa — 224 páginas — más Integraciones/MVP1, MVP2, gobierno de aplicaciones/aplicativos/datos, identidad digital, catálogos y documentos adicionales); no se encontró ninguna mención de este habilitador con ese nombre ni variantes cercanas | AS63: No encontrada
A64: 59 | F64: Superate | T64: Sin información | U64: Sin información | V64: Sin información | W64: Sin información | X64: Sin información | Y64: Sin información | Z64: Sin información | AA64: 0 | AB64: 0 | AC64: 0 | AE64: Mission Critical | AH64: =IF(AND(AF64>=3,AG64>=3),"Invest",IF(AND(AF64>=3,AG64<3),"Migrate",IF(AND(AF64<3,AG64>=3),"Tolerate","Eliminate"))) -> Eliminate | AI64: Sin información | AJ64: Sin información | AK64: Active | AL64: Sin información | AM64: Sin información | AN64: Sin información | AP64: DED | AR64: Búsqueda exhaustiva en Repositorio TD-Ecosistema Digital VPAF el 10-sep-2026 (wiki institucional completa — 224 páginas — más Integraciones/MVP1, MVP2, gobierno de aplicaciones/aplicativos/datos, identidad digital, catálogos y documentos adicionales); no se encontró ninguna mención de este habilitador con ese nombre ni variantes cercanas | AS64: No encontrada
A65: 60 | F65: Formando formadores | T65: Sin información | U65: Sin información | V65: Sin información | W65: Sin información | X65: Sin información | Y65: Sin información | Z65: Sin información | AA65: 0 | AB65: 0 | AC65: 0 | AE65: Mission Critical | AH65: =IF(AND(AF65>=3,AG65>=3),"Invest",IF(AND(AF65>=3,AG65<3),"Migrate",IF(AND(AF65<3,AG65>=3),"Tolerate","Eliminate"))) -> Eliminate | AI65: Sin información | AJ65: Sin información | AK65: Active | AL65: Sin información | AM65: Sin información | AN65: Sin información | AP65: DED | AR65: Búsqueda exhaustiva en Repositorio TD-Ecosistema Digital VPAF el 10-sep-2026 (wiki institucional completa — 224 páginas — más Integraciones/MVP1, MVP2, gobierno de aplicaciones/aplicativos/datos, identidad digital, catálogos y documentos adicionales); no se encontró ninguna mención de este habilitador con ese nombre ni variantes cercanas | AS65: No encontrada
A66: 61 | F66: Centro Virtual de aprendizaje | T66: Sin información | U66: Sin información | V66: Sin información | W66: Sin información | X66: Sin información | Y66: Sin información | Z66: Sin información | AA66: 0 | AB66: 0 | AC66: 0 | AE66: Mission Critical | AH66: =IF(AND(AF66>=3,AG66>=3),"Invest",IF(AND(AF66>=3,AG66<3),"Migrate",IF(AND(AF66<3,AG66>=3),"Tolerate","Eliminate"))) -> Eliminate | AI66: Sin información | AJ66: Sin información | AK66: Active | AL66: Sin información | AM66: Sin información | AN66: Sin información | AP66: DED | AR66: Búsqueda exhaustiva en Repositorio TD-Ecosistema Digital VPAF el 10-sep-2026 (wiki institucional completa — 224 páginas — más Integraciones/MVP1, MVP2, gobierno de aplicaciones/aplicativos/datos, identidad digital, catálogos y documentos adicionales); no se encontró ninguna mención de este habilitador con ese nombre ni variantes cercanas | AS66: No encontrada
A67: 62 | F67: innermetrix | T67: Sin información | U67: Sin información | V67: Sin información | W67: Sin información | X67: Sin información | Y67: Sin información | Z67: Sin información | AA67: 0 | AB67: 0 | AC67: 0 | AE67: Mission Critical | AH67: =IF(AND(AF67>=3,AG67>=3),"Invest",IF(AND(AF67>=3,AG67<3),"Migrate",IF(AND(AF67<3,AG67>=3),"Tolerate","Eliminate"))) -> Eliminate | AI67: Sin información | AJ67: Sin información | AK67: Active | AL67: Sin información | AM67: Sin información | AN67: Sin información | AR67: Búsqueda exhaustiva en Repositorio TD-Ecosistema Digital VPAF el 10-sep-2026 (wiki institucional completa — 224 páginas — más Integraciones/MVP1, MVP2, gobierno de aplicaciones/aplicativos/datos, identidad digital, catálogos y documentos adicionales); no se encontró ninguna mención de este habilitador con ese nombre ni variantes cercanas | AS67: No encontrada
A68: 63 | F68: Tec.doc | G68: Repositorio institucional de gestión documental del Tec de Monterrey. Expone un API JSON-RPC 2.0 (endpoint POST /documento, método CrearDocumento) que recibe un archivo en base64 más metadatos (repositorio, tipo de documento, institución, nivel de acceso) y devuelve una URL del documento con token SAS para descarga. | S68: API Gateway institucional (APIM) / JSON-RPC 2.0 | T68: Sin información | U68: https://apigateway-devl.tec.mx/documentos-institucionales/metodos-gestion | V68: Sin información | W68: Sin información | X68: Sin información | Y68: Sin información | Z68: Sin información | AA68: 0 | AB68: 0 | AC68: 0 | AE68: Mission Critical | AH68: =IF(AND(AF68>=3,AG68>=3),"Invest",IF(AND(AF68>=3,AG68<3),"Migrate",IF(AND(AF68<3,AG68>=3),"Tolerate","Eliminate"))) -> Eliminate | AI68: Sin información | AJ68: Sin información | AK68: Active | AL68: 1 documentada (JOB-015) | AM68: Sin información | AN68: Sin información | AO68: Nota (10-sep-2026, fuente Repositorio TD-Ecosistema Digital VPAF): TEC.doc está confirmado como componente de la familia "Tec.X" en FUD/Pages/Componentes.html (junto a TEC.cognitive, TEC.credentials, TEC.data, TEC.gpt, TEC.id, TEC.IoT, TEC.mobi, TEC.notify, TEC.pay, TEC.sandbox, TEC.sign, TEC.verse), aunque esa entrada del catálogo está vacía. La descripción funcional viene del contrato de integración JOB-015 ("Descarga de Folleto", carpeta Integraciones/MVP1/Flujo de registro de URL de folletos): Pulsar toma folletos informativos (PDF) desde SharePoint (Microsoft Graph API) y los da de alta en TEC.doc (idHabilitador=21 "VPAFMARKET", idRepositorio=44 "repvpafmarket", idTipoDocumento=422 "Folleto Informativo"); TEC.doc devuelve la URL/SAS del documento, que después se escribe en SEA API (tabla taxonomiarepositorio). El propio documento aclara que este contrato no se ha verificado formalmente con el equipo dueño de TEC.doc — no se nombra un responsable específico, solo "equipo de TEC.doc" como stakeholder genérico. Pendiente confirmar con ese equipo antes de dar estos datos por definitivos. | AR68: Repositorio TD-Ecosistema Digital VPAF/Integraciones/MVP1/Flujo de registro de URL de folletos/JOB-015_Descarga_de_Folleto.docx (contrato de integración); confirmado como componente en FUD/Pages/Componentes.html | AS68: Parcial / relacionada
A69: 64 | F69: Tec.cognitive | J69: Manuel Terán Melgarejo (Gerencia del Centro de Arquitectura y Habilitación de IA) | T69: Sin información | U69: Sin información | V69: Sin información | W69: Sin información | X69: Sin información | Y69: Sin información | Z69: Sin información | AA69: 0 | AB69: 0 | AC69: 0 | AE69: Mission Critical | AH69: =IF(AND(AF69>=3,AG69>=3),"Invest",IF(AND(AF69>=3,AG69<3),"Migrate",IF(AND(AF69<3,AG69>=3),"Tolerate","Eliminate"))) -> Eliminate | AI69: Sin información | AJ69: Sin información | AK69: Active | AL69: Sin información | AM69: Sin información | AN69: Sin información | AO69: Nota (10-sep-2026, fuente Repositorio TD-Ecosistema Digital VPAF): se encontró la página de wiki institucional FUD/Pages/TEC.cognitive.html (topicHeader "COMPONENTE", publicada 17-abr-2023, dueño Manuel Terán Melgarejo — Gerencia del Centro de Arquitectura y Habilitación de IA). Confirma que TEC.cognitive existe como componente real de la familia "Tec.X", pero todas sus secciones de contenido (Introducción, Requisitos previos, Guía de inicio rápido, Documentación de API, Casos de referencia, etc.) están vacías — es una plantilla sin llenar (única entrada de "Evolución del documento": v1.0, 13-abr-2023, "Documento base"). No se encontró ninguna descripción funcional de qué hace o para qué se usa; se deja "Descripción" sin cambiar hasta que se consiga esa información con el equipo dueño. | AR69: Repositorio TD-Ecosistema Digital VPAF/FUD/Pages/TEC.cognitive.html | AS69: Parcial / relacionada
A70: 65 | E70: 5147-HTI-001-TRXC | F70: Marketplace de Socios Formadores | G70: Plataforma para conectar académicos con Socios Formadores para colaborar en proyectos. | L70: daniel_ayala@tec.mx | M70: gerardo.suarez@tec.mx | N70: mariano_uriostegui@tec.mx | O70: mariano_uriostegui@tec.mx | Q70: Custom Development | S70: Node.js, Java | T70: https://www.mpstec.mx/ | AE70: Medium | AH70: Eliminate | AO70: Aplicativo hallado dentro de una fila con celdas combinadas (merge A28:A30 / F28:F30 / G28:G30, heredado del archivo fuente 'E1.1_Inventario autoritativo de aplicativos (1).xlsx' de la carpeta 'Nueva Evidencia'), compartida visualmente con 'Marketplace de Talento' (#25) y 'Nimbi' (#26). No tenía # ni fila propia. Se formaliza aquí como registro independiente (E1.1.2, adición pura, no se modificó ni eliminó nada del E1.1/E1.1.1) tomando los valores que sí eran propios y distintivos de esta fila en el archivo fuente (columna 'Producto_Componente:Title' contenía el nombre real; ID Habilitador, URL, responsables, stack y disposición TIME eran valores propios de la fila). PENDIENTE: validar con el equipo dueño que la lectura de estas columnas (afectadas por el corrimiento de columnas conocido en este bloque) es correcta antes de dar el registro por definitivo. Fuente: Nueva Evidencia, 15-sep-2026. Añadido: 16-sep-2026. | AP70: VEC
A71: 66 | E71: 0222-HTI-010-SISO | F71: GURJOBS | K71: aoropeza@tec.mx | M71: aoropeza@tec.mx | N71: antonio.jimenez@tec.mx | P71: Keycloak + Azure | Q71: Custom Development | R71: Hybrid | S71: Keycloak + Azure (auth) | AE71: Medium | AF71: 3 | AH71: Migrate | AK71: Active | AO71: Aplicativo hallado dentro de una fila con celdas combinadas (merge A28:A30 / F28:F30 / G28:G30, heredado del archivo fuente 'E1.1_Inventario autoritativo de aplicativos (1).xlsx' de la carpeta 'Nueva Evidencia'), compartida visualmente con 'Marketplace de Talento' (#25) y 'Marketplace de Socios Formadores' (#66). No tenía # ni fila propia. Se formaliza aquí como registro independiente (E1.1.2, adición pura, no se modificó ni eliminó nada del E1.1/E1.1.1) tomando los valores que sí eran propios y distintivos de esta fila (columna 'Producto_Componente:Title' contenía el nombre real; ID Habilitador, responsables, proveedor, stack, hosting y disposición TIME eran valores propios de la fila). La 'Descripción' que aparecía en columnas contiguas de esta fila ('Conecta a prospectos egresados con empleadores') es en realidad la de 'Marketplace de Talento' (arrastrada por el mismo corrimiento/merge de columnas), por lo que NO se usó — se deja 'Descripción' sin información hasta confirmar con el equipo. PENDIENTE: validar con el equipo dueño la lectura completa de esta fila antes de darla por definitiva. Fuente: Nueva Evidencia, 15-sep-2026. Añadido: 16-sep-2026. | AP71: VEC
A72: 67 | E72: Sin información / por confirmar | F72: vForm (Plataforma de Gestión de Innovación Educativa) | G72: Plataforma SaaS (proveedor Vinko Digital/Vinko SPA) para la gestión de convocatorias de innovación educativa: postulación, revisión y seguimiento de participantes de los programas "Novus" y "Registro i" de CEDDIE Región Monterrey. | H72: Sin información / por confirmar | I72: Sin información / por confirmar | J72: Claudia Erika García López (CEDDIE Región Monterrey, L00633917) — claudia.e.garcia@tec.mx | K72: Edna Edith Olivo Rivera (Devteam Head, Dirección de Desarrollo-Techvolution 2.0, L00765933) — eeolivo@tec.mx | L72: Héctor Jacobo Ríos Quiroz (Registro i, L01391151) y Mónica Medellín Estrada (Novus, L03140344) — Líderes de Soporte Funcional, Experimentación y Medición de Impacto | M72: Juan Pablo Giordano (Vinko Digital, Líder de Soporte Técnico del Proveedor) — juanpablo@vinkodigital.com | N72: TI de Vinko Digital (proveedor) — la operación de infraestructura y plataforma está incluida en el licenciamiento SaaS | O72: Soporte Vinko Digital (soporte@vinkodigital.com, WhatsApp +56 9 4165 0442); Soporte Técnico N2 del Tec: José Patricio Simbrón, Cynthia Rodulfo Hernández | P72: Vinko Digital / Vinko SPA (Chile) | Q72: Solución adquirida (SaaS) — sin desarrollo a la medida; la configuración de parámetros y convocatorias se realiza dentro de la propia plataforma | R72: Cloud-SaaS — Heroku (aplicación, con escalamiento horizontal automático vía HireFire) + AWS (servidores de procesamiento y base de datos en Virginia, USA; repositorio de archivos en S3, Ohio, USA) | S72: Heroku (PaaS) + AWS S3; monitoreo Appsignal (general), logDNA (logs), Sentry (errores), Sqreen (seguridad/WAF); análisis estático Brakeman + GitHub Security Alerts | T72: https://innovation.tec.mx | U72: Sin información / por confirmar | V72: https://innovation-test.tec.mx | W72: Sin información / por confirmar | X72: Sin información / por confirmar | Y72: Contrato SaaS vigente hasta 27-mar-2026 (renovación anual — "Contrato SaaS vForm - Tec de Monterrey 2025_VF.docx") | Z72: 8,145 usuarios totales (2024; licenciamiento con usuarios ilimitados). Concurrencia histórica: Registro i 550 postulaciones en 6 convocatorias (2024); Novus 277 postulaciones en 5 convocatorias (2024). Capacidad soportada: 1,000 usuarios simultáneos/hora (prueba de carga JMeter del proveedor). | AA72: 13637 | AB72: 0 | AC72: 0 | AD72: 0 | AE72: Sin evaluar | AH72: =IF(OR(AC53="",AD53=""),"Sin evaluar",IF(AND(AC53>=3,AD53>=3),"Invest",IF(AND(AC53>=3,AD53<3),"Migrate",IF(AND(AC53<3,AD53>=3),"Tolerate","Eliminate")))) -> Eliminate | AI72: Sin información / por confirmar | AJ72: Sin información / por confirmar | AK72: Active | AL72: 5 integraciones directas confirmadas (Volumen Operativo M2O): Banner 9, DWH, BO (BusinessObjects), SSFF (SuccessFactors), MDM; 1 integración indirecta: SAMP → MDM. | AM72: Sin información / por confirmar | AN72: Sin información / por confirmar | AO72: Hallazgo de sexta pasada (10-sep-2026): habilitador no incluido en el Inventory APM (v17/v18/v19) ni en los 31 TDD existentes hasta esta fecha. Encontrado en la carpeta previamente sin escanear "Documentacion_Digital_Nueva" (subcarpeta IO-M2O), agregada por el usuario al repositorio "Repositorio TD-Ecosistema Digital VPAF". Se confirmó mediante tres documentos M2O reales y llenos (no plantillas vacías): "IO-M2O-Presupuesto y Contrato_Habilitador-yyyyddmm.docx", "IO-M2O-Volumen Operativo_Habilitador-yyyyddmm.docx" e "IO-M2O-OLA-Habilitador-yyyyddmm.docx". Contactos y roles, disponibilidad objetivo (24/7, uptime ≥98% con penalización contractual del 3% por incumplimiento), esquema de escalamiento (HireFire/Heroku), y ventana de atención del proveedor (lunes a viernes 08:30–18:30 hora de Santiago de Chile) citados textualmente de esos documentos. Se creó el TDD-APM-vForm (TDD #11 de esta iniciativa) a partir de esta misma documentación. Nota de calidad de dato: los extractos ".md" de la subcarpeta "_ia-ready" de esa carpeta son resúmenes generados por una prueba de concepto interna con IA local (ollama/qwen3:8b, confianza reportada 64–75%) y no se usaron como fuente autoritativa; todos los datos de esta fila provienen de la lectura directa de los documentos Word originales. Todos los campos marcados "Sin información / por confirmar" (ID Habilitador, Producto_Componente, URLs de desarrollo, versión, fecha de primer día en producción, criticidad/puntaje VN-ST, clasificación de datos, etiquetas de cumplimiento) no cuentan con evidencia documental y deben levantarse con el equipo de Arquitectura y con CEDDIE Región Monterrey. | AP72: Sin información / por confirmar — no forma parte de los ecosistemas ya catalogados (VEC/TLG/Transversal); pendiente definir con Arquitectura | AR72: Documentacion_Digital_Nueva/IO-M2O (Presupuesto y Contrato, Volumen Operativo, OLA — documentos M2O reales y llenos); no forma parte del sitio de SharePoint crawleado (carpeta local agregada por el usuario, sexta pasada 10-sep-2026) | AS72: Confirmada

Sheet TIME Assessment
B2: MATRIZ DE CALIFICACIÓN — VALOR DE NEGOCIO
B3: Criterio | D3: Descripción
B4: Alineación Estratégica | D4: Grado en que la aplicación apoya la estrategia corporativa y los indicadores clave de la organización.
B5: Impacto en Ingresos / Costos | D5: Contribución directa a la generación de ingresos o a la reducción de costos.
B6: Base de Usuarios y Alcance | D6: Número de usuarios activos y amplitud de las áreas de negocio atendidas.
B7: Criticidad del Proceso | D7: Dependencia operativa — ¿qué pasa si la aplicación no está disponible?
B8: Ventaja Competitiva | D8: ¿La aplicación permite diferenciación frente a la competencia?
B11: ESCALA DE CALIFICACIÓN | 5 = Esencial · 4 = Importante · 3 = Moderado · 2 = Marginal · 1 = Mínimo
B13: MATRIZ DE CALIFICACIÓN — SALUD TÉCNICA
B14: Criterio | D14: Descripción
B15: Calidad de Arquitectura | D15: Cumplimiento de los estándares de arquitectura vigentes (API-first, microservicios, cloud-native).
B16: Estado de Soporte del Proveedor | D16: Soporte activo del proveedor. Fecha de EOL/EOS vs. hoy. Cadencia de parches de seguridad.
B17: Escalabilidad y Desempeño | D17: Capacidad para manejar la carga actual y proyectada. Tasa de cumplimiento de SLA.
B18: Mantenibilidad | D18: Calidad del código, cobertura de documentación, nivel de automatización de despliegues.
B19: Postura de Seguridad | D19: CVEs conocidos, resultado del último pen-test, cumplimiento de los benchmarks OWASP/CIS.
B22: ESCALA DE CALIFICACIÓN | 5 = Excelente · 4 = Bueno · 3 = Aceptable · 2 = Deficiente · 1 = Crítico / EOL
B24: MATRIZ DE CUADRANTES TIME — Lógica de Calificación Compuesta
D25: Salud Técnica: Baja (1-2) | G25: Salud Técnica: Alta (3-5)
B26: VN: Alta (3-5) | D26: MIGRATE -- VN Alta + ST Baja -- Modernizar o reemplazar la plataforma | G26: INVEST -- VN Alta + ST Alta -- Mejorar y hacer crecer
B27: VN: Baja (1-2) | D27: ELIMINATE -- VN Baja + ST Baja -- Dar de baja lo antes posible | G27: TOLERATE -- VN Baja + ST Alta -- Minimizar el gasto, planear su retiro

Sheet Dashboard
B2: TABLERO DEL PORTAFOLIO DE APLICACIONES — TIME DE GARTNER
B3: Generado: 24 jul 2026 · Fuente: hoja Inventory
B5: ⬛ Portafolio por Disposición TIME
B6: INVEST | F6: MIGRATE | J6: TOLERATE | N6: ELIMINATE
B7: =COUNTIF(Inventory!AH:AH,"Invest") -> 13 | F7: =COUNTIF(Inventory!AH:AH,"Migrate") -> 32 | J7: =COUNTIF(Inventory!AH:AH,"Tolerate") -> 2 | N7: =COUNTIF(Inventory!AH:AH,"Eliminate") -> 22
B12: 💰 Costo Anual por Disposición TIME
B13: Costo Total INVEST | F13: Costo Total MIGRATE | J13: Costo Total TOLERATE | N13: Costo Total ELIMINATE
B14: =SUMIF(Inventory!AH:AH,"Invest",Inventory!AD:AD) -> 0 | F14: =SUMIF(Inventory!AH:AH,"Migrate",Inventory!AD:AD) -> 0 | J14: =SUMIF(Inventory!AH:AH,"Tolerate",Inventory!AD:AD) -> 0 | N14: =SUMIF(Inventory!AH:AH,"Eliminate",Inventory!AD:AD) -> 0
B16: ⚠️ Indicadores de Riesgo
B17: EOL en <12 Meses | F17: EOL ya Vencido | J17: Total de Aplicaciones | N17: Costo Total Anual
B18: =COUNTIFS(Inventory!Y:Y,"<="&(TODAY()+365),Inventory!Y:Y,">="&TODAY()) -> 0 | F18: =COUNTIFS(Inventory!Y:Y,"<"&TODAY(),Inventory!Y:Y,"<>"&"") -> 0 | J18: =COUNTA(Inventory!F4:F1001)-COUNTIF(Inventory!F4:F1001,"") -> -864 | N18: =SUM(Inventory!AD:AD) -> 0
B20: 🔴 Aplicaciones por Criticidad
B21: Mission Critical | F21: High | J21: Medium | N21: Low
B22: =COUNTIF(Inventory!AE:AE,"Mission Critical") -> 23 | F22: =COUNTIF(Inventory!AE:AE,"High") -> 16 | J22: =COUNTIF(Inventory!AE:AE,"Medium") -> 25 | N22: =COUNTIF(Inventory!AE:AE,"Low") -> 4
B24: ☁️ Aplicaciones por Modelo de Hosting
B25: On-Premises | F25: Cloud-SaaS | J25: Cloud-IaaS/PaaS | N25: Hybrid
B26: =COUNTIF(Inventory!R:R,"On-Premises") -> 1 | F26: =COUNTIF(Inventory!R:R,"Cloud-SaaS") -> 36 | J26: =COUNTIF(Inventory!R:R,"Cloud-IaaS")+COUNTIF(Inventory!R:R,"Cloud-PaaS") -> 2 | N26: =COUNTIF(Inventory!R:R,"Hybrid") -> 6
B29: 📈 Cobertura de Datos (Inventory, filas 4–52)
B30: Responsable Técnico | F30: Usuarios Activos | J30: Dirección URL (PROD) | N30: Clasificación de Datos
B31: =1-COUNTIF(Inventory!K4:K54,"Sin información")/COUNTA(Inventory!F4:F54) -> 0.89795918 | F31: =1-COUNTIF(Inventory!Z4:Z54,"Sin información")/COUNTA(Inventory!F4:F54) -> 0.57142857 | J31: =1-COUNTIF(Inventory!T4:T54,"Sin información")/COUNTA(Inventory!F4:F54) -> 0.36734694 | N31: =1-COUNTIF(Inventory!AM4:AM54,"Sin información")/COUNTA(Inventory!F4:F54) -> 0.34693878
B34: Datos para gráficas (no editar)
B35: Disposición TIME | C35: Aplicaciones | E35: Criticidad | F35: Aplicaciones | H35: Hosting | I35: Aplicaciones
B36: Invest | C36: =B7 -> 13 | E36: Mission Critical | F36: =B22 -> 23 | H36: On-Premises | I36: =B26 -> 1
B37: Migrate | C37: =F7 -> 32 | E37: High | F37: =F22 -> 16 | H37: Cloud-SaaS | I37: =F26 -> 36
B38: Tolerate | C38: =J7 -> 2 | E38: Medium | F38: =J22 -> 25 | H38: Cloud-IaaS/PaaS | I38: =J26 -> 2
B39: Eliminate | C39: =N7 -> 22 | E39: Low | F39: =N22 -> 4 | H39: Hybrid | I39: =N26 -> 6

Sheet Process
B2: PROCESO DE GOBIERNO APM — Roles, Cadencia y Actividades
B3: 👥 Matriz RACI — Roles Clave
B4: Actividad | C4: Cadencia | D4: Responsable | E4: RACI | F4: Descripción y Entregables
B5: Coordinador APM | C5: — | D5: Mantiene el inventario, programa las revisiones, consolida las calificaciones. R para todas las actividades de APM.
B6: Dueño de la Aplicación | C6: — | D6: Interesado de negocio o de TI responsable de cada aplicación. R para la captura de calificaciones.
B7: Arquitecto Empresarial | C7: — | D7: Define los estándares, valida las recomendaciones TIME, es dueño del marco APM. A para las disposiciones.
B8: CIO / Director de TI | C8: — | D8: Aprueba las decisiones del portafolio (Invest, Migrate, Eliminate). A para el impacto presupuestal.
B9: Socio de Negocio de Finanzas | C9: — | D9: Valida los datos de costo, los vincula al presupuesto de TI. C para los campos de costo.
B10: Oficial de Seguridad | C10: — | D10: Revisa la clasificación de datos y las etiquetas de cumplimiento. C para los campos de riesgo.
B13: 📅 Cadencia de Gobierno
B14: Actividad | C14: Cadencia | D14: Responsable | E14: RACI | F14: Descripción y Entregables
B15: Revisión Anual del Portafolio | C15: Anual (T1) | D15: Coordinador APM | E15: R-Arquitecto Empresarial / A-CIO | F15: Reevaluación completa de todas las aplicaciones. Actualizar todas las calificaciones, costos, fechas de EOL, disposiciones y elementos de la hoja de ruta. Entregable: Inventory actualizado + resumen ejecutivo.
B16: Revisión Trimestral de Salud | C16: Trimestral | D16: Coordinador APM | E16: R-Dueño de la Aplicación / I-CIO | F16: Enfocado en las aplicaciones Migrate y Eliminate. Revisar el avance de proyectos, costos actualizados y alertas de riesgo. Entregable: reporte de estatus para el liderazgo de TI.
B17: Alta de Nueva Aplicación | C17: Bajo demanda | D17: Dueño de la Aplicación | E17: R-Arquitecto Empresarial / A-CIO | F17: Toda aplicación nueva debe registrarse antes de su puesta en producción. Completar todos los campos de Inventory. La disposición TIME se define de forma provisional; se confirma en la siguiente revisión anual.
B18: Aprobación de Baja | C18: Bajo demanda | D18: Coordinador APM | E18: R-CIO / C-Finanzas / I-Seguridad | F18: Aprobación formal para dar de baja una aplicación. Actualizar Status → Retiring, documentar el plan de migración, registrar los ahorros. Entregable: acta de baja firmada.
B19: Revisión de Emergencia | C19: Ad hoc | D19: Arquitecto Empresarial | E19: R-CIO / A-Coordinador APM | F19: Se activa por EOL crítico de un proveedor, brecha de seguridad o evento de M&A. Reevaluación TIME acelerada para las aplicaciones afectadas.
B20: Conciliación de Costos | C20: Semestral | D20: Enlace de Finanzas | E20: R-Coordinador APM / A-CIO | F20: Conciliar facturas de licencias, gasto de infraestructura y contratos de soporte contra los campos de costo de Inventory. Actualizar las columnas O, P, Q.
B23: ✅ Lista de Verificación — Alta de Nueva Aplicación
B24: ☐ Nombre de la aplicación, proveedor y tipo confirmados
B25: ☐ Dueño de negocio y dueño de TI asignados
B26: ☐ Modelo de hosting y stack tecnológico documentados
B27: ☐ Fecha de puesta en producción confirmada; fecha de EOL del proveedor investigada
B28: ☐ Estimado de costo anual (licencias + infraestructura + soporte) capturado
B29: ☐ Valor de Negocio y Salud Técnica calificados inicialmente (1–5)
B30: ☐ Clasificación de Datos y Etiquetas de Cumplimiento definidas por el Oficial de Seguridad
B31: ☐ Inventario de integraciones completado (conteo y lista de sistemas)
B32: ☐ Disposición TIME revisada con el Arquitecto Empresarial
B33: ☐ Registrada en la hoja Inventory antes de la autorización de puesta en producción

Sheet Lookups
B2: Tipo de Aplicación | C2: Hosting | D2: Criticidad | E2: Estatus | F2: Clasificación de Datos | G2: Disposición TIME | H2: Producto_Componente:Title | I2: Producto_Componente
B3: Commercial Off-the-Shelf | C3: On-Premises | D3: Mission Critical | E3: Active | F3: Public | G3: Invest | H3: 01. Aprendizaje y Enseñanza | I3: AI01. TEC.bot
B4: SaaS | C4: Cloud-IaaS | D4: High | E4: Under Evaluation | F4: Internal | G4: Migrate | H4: 03. Facultad | I4: ATV01. Compra y Pago
B5: Custom Development | C5: Cloud-PaaS | D5: Medium | E5: Retiring | F5: Confidential | G5: Tolerate | H5: 04. Finanzas | I5: ATV02. Gestión Académica
B6: ERP Module | C6: Cloud-SaaS | D6: Low | E6: Retired | F6: Restricted | G6: Eliminate | H6: 06. Proyección y Vinculación | I6: ATV03-1. Atracción y Venta
B7: Open Source | C7: Hybrid | E7: Suspended | H7: 08. Colaboradores | I7: ATV04. Gestión de la Oferta
B8: Legacy | C8: Colocation | H8: 09. Inteligencia Artificial | I8: CLB05. Gestión de Talento
B9: Platform Service | H9: 10. Plataforma de Datos | I9: DD01. TEC.portal
H10: 11. Distribución Digital | I10: DD03. TEC.sites
H11: 15. Aprendizaje para el futuro | I11: DP01. TEC.data
H12: 16. Línea de Servicio | I12: ECD03- APF Vivencia y Gestión del Aprendizaje
H13: 18. APF Ecosistema Digital | I13: FAC02. Desarrollo de Facultad
I14: FNC02. Facturación
I15: FNC05. Información financiera y fiscal
I16: HT03. Banner
I17: HT04. Salesforce
I18: MKT03. Promoción
I19: TL01. Plataformas de Aprendizaje y Evaluación

Sheet Hoja1
A1: 1er grupo | D1: sea
A2: sea | D2: pase
A3: pase | D3: vtex
A4: vtex | D4: portal unificado
A5: portal unificado | D5: cypher
A6: cypher | D6: TLG
A7: Grupo2 | D7: DRUPAL
A8: TLG | D8: TEC BOT
A9: DRUPAL | D9: OPEN TEXT
A10: TEC BOT | D10: OPEN PAY
A11: OPEN TEXT | D11: FUD
A12: OPEN PAY | D12: ACREDIBLE
... A26: BANER | D26: PLataforma web centro de idiomas
A27: MARKET TEC
A28: gRUPO 5
A29: Canvas
A30: Portales VEC
A31: PLataforma web centro de idiomas
